
<text>


 <page>
<ph>481</ph><p>090-241a</p>
@##/ /rgya gar skad du/ sarba ta thA ga ta uSh+NI Sha bi dza ya nA ma 
d+hA ra NI kalpa sa hi ta/ bod skad du/ de bzhin gshegs pa thams cad kyi gtsug tor rnam par rgyal ba zhes bya ba'i gzungs rtog pa dang bcas pa/ sangs rgyas dang byang chub sems dpa' thams cad la phyag 'tshal lo/ /'di skad bdag gis thos pa dus gcig na/ bcom 
</page>

 <page>
<ph>482</ph><p>090-241b</p>
ldan 'das de bzhin gshegs pa dgra bcom pa yang dag par rdzogs pa'i sangs rgyas tshe dpag tu med pa bde ba can gyi chos yang dag par sdud pa'i khang bzangs mchog na nye bar bzhugs so/ /de nas 'khor gyi dkyil 'khor la nye bar gzigs te/ 'phags pa spyan ras gzigs 
dbang phyug la bka' stsal pa/ kye byang chub sems dpa' sems dpa' chen po rigs kyi bu dang / rigs kyi bu mo sdug bsngal ba nad kyis yongs su gzir ba'i sems can tshe thung ba rnams yod de/ de rnams kyi phyir sems can thams cad la kun du gzigs pa'i mtshan 
gyi dpal de bzhin gshegs pa thams cad kyi gtsug tor rnam par rgyal ba zhes bya ba'i gzungs 'di nyid 'chang ba dang / klog pa dang / gzhan la rgya cher yang dag par bstan pa'i phyir yun ring por gnas par bsgrub pa'i ched du bcom ldan 'das kyis thams cad dang ldan pa'i 'khor 
gyi dkyil 'khor la gzigs te/ kun du gzigs pa'i dpal zhes bya ba'i ting nge 'dzin la snyoms par zhugs te/ de bzhin gshegs pa thams cad kyi gtsug tor rnam par rgyal ba zhes bya ba'i gzungs 'di bka' stsal pa/ oM na mo b+ha ga wa te sarba trai lo kya pra ti bi shiSh+TA 
ya bud d+hA ya te na maH/ tad+ya thA/ o~M b+h+rUM b+h+rUM b+h+rUM/ sho d+ha ya sho d+ha ya/ bi sho d+ha ya/ bi sho d+ha ya/ a sa ma sa man+ta a ba b+hA sa s+pha ra Na ga ti/ ga ga na swa b+hA ba bi shud d+he/ uSh+NI Sha bi dza ya pa ri shud d+he/ a b+hi Shiny+tsan+tu mAM/ sarba ta thA ga ta su ga ta bar ba tsa na/ a mr-i ta a b+hi 
She kair/ ma hA mu dra man+t+ra pa daiH/ A ha ra A ha ra/ ma ma A yuH/ san d+ha ra Ni/ sho d+ha ya sho d+ha ya/ pi sho d+ha ya bi sho d+ha ya/ ga ga na swa b+hA ba bi shud d+he/ uSh+NI Sha bi dza ya pa ri shud d+he/ sa ha sra ra smi sany+tso di te/ sarba ta thA ga ta a wa lo ki ni/ ShaT pA ra mi tA pA ri pU ra Ni/ 
sarba ta thA ga ta mA te da sha b+hU mi pra tiSh+Thi te/ sarba ta thA ga ta hr-i da ya a d+hiSh+ThA na a d+hiSh+Thi te/ mu dre mu dre/ ma hA mu dre/ ma hA mu dre/ badzra kA ya saM ha ta na/ pa ri shud d+he/ sarba karma A wa ra Na bi shud d+he/ pra ti ni brta ya/ ma ma A yur bi shud d+he/ sarba ta thA ga ta sa ma ya a 
</page>

 <page>
<ph>483</ph><p>090-242a</p>
d+hiSh+ThA na a d+hiSh+Thi te/ o~M mu ni mu ni/ ma hA mu ni/ bi mu ni bi mu ni/ ma hA bi mu ni/ ma ti ma ti/ ma hA ma ti/ ma ma ti/ su ma ti/ ta thA tA b+hA ta ko Ti/ pa ri shud d+he/ bi s+phu Ta/ bud d+hi shud d+he/ he he/ dza ya dza ya/ bi dza ya bi dza ya/ sma ra sma ra/ s+pha ra s+pha ra/ 
s+phA ra ya s+phA ra ya/ sarba bud d+ha a d+hiSh+ThA na a d+hiSh+Thi te/ shud d+he shud d+he/ bud d+he bud d+he/ badzre badzre/ ma hA badzre/ su badzre/ badzra gar+b+he/ dza ya gar+b+he/ bi dza ya gar+b+he/ bi dza ya gar+b+he/ badzra dz+wA lA gar+b+he/ badzra ud b+ha be/ badzra saM b+ha be/ badzre badzrI ni/ badzram+b+ha ba tu/ ma ma sha 
rI raM sarba satwA nAny+tsa kA ya pa ri shud d+hir b+ha ba tu/ sa dA me sarba ga ti pa ri shud d+hish+tsa/ sarba ta thA ga tA mAM sa mA shwA sa yan+tu/ bud d+h+ya bud d+h+ya/ sid d+h+ya sid d+h+ya/ bo d+ha ya bo d+ha ya/ bi bo d+ha ya bi bo d+ha ya/ mo tsa ya mo tsa ya/ bi mo tsa ya bi mo tsa ya/ sho d+ha ya sho d+ha ya/ bi 
sho d+ha ya bi sho d+ha ya/ sa man+tA na mo tsa ya mo tsa ya/ sa man+ta ra smi pa ri shud d+he/ sarba ta thA ga ta hr-i da ya/ a d+hiSh+ThA na a d+hiSh+Thi te/ mu dre mu dre/ ma hA mu dre ma hA mu drA man+t+ra pa daiHswA hA/ gtsug tor rnam par rgyal ba zhes bya ba sdig pa dang sgrib pa thams cad rnam par sbyong 
ba/ ngan song thams cad rgyun gcod pa 'di yi ger bris te/ mchod rten gyi srog shing gi steng du bzhag la/ zla ba nya ba'i tshe khrus byas te lan stong rtsa brgyad brjod na tshe zad pa las tshe phyir nur bar 'gyur ro/ /ngan song las myur du thar te/ sgrib pa rnams dag nas 
bla na med pa'i byang chub thob par 'gyur ro/ /dud 'gro rnams kyis thos na yang de rnams ngan song gi tha ma yin te/ byang chub ma thob kyi bar du mtho ris rgyal po'i rigs sam/ bram ze'i rigs sam/ tshong dpon gyi rigs sam/ khyim bdag gi rigs shing sA la 
chen po lta bu'i nang du skye bar 'gyur ro/ /mchod rten de'i grib mas phog gam/ rdul gyis btab kyang rung ste ngan song du 'gro bar mi 'gyur ro/ /bcom ldan 'das kyis de skad ces bka' stsal nas/ byang chub sems dpa' sems dpa' chen po 'phags pa spyan 
</page>

 <page>
<ph>484</ph><p>090-242b</p>
ras gzigs dbang phyug yi rangs te mngon par bstod do// //'phags pa gtsug tor rnam par rgyal ba'i gzungs rtog pa dang bcas pa rdzogs so// </page>


</text>