
<text>


 <page>
<ph>421</ph><p>091-211a</p>
@#/ /lha'i dbang po brgya byin gyis bstod pa/ /dus gsum 'khor ba'i sdug bsngal chen po dang / /'dod chags zhe sdang 
gti mug gsum gyi rgyus/ /sdig smin las grub lha dang lha ma yin/ /dmyal tshogs me ltar 'bar ba'i gnas 'di ru/ /sha khrag dmar la rol pa'i lha mo khyod/ /lha yi g.yul ngo rgyal bar zhal 'ches la/ /lha ma yin gyi dpung rnams brlag par mdzod/ /
</page>

 <page>
<ph>422</ph><p>091-211b</p>
ces bstod do rdzogs so// </page>


</text>