<?xml version="1.0" encoding="UTF-8"?>
<outline>
<name>Wanli</name>
<creator type="hasScribe">Bruno Laine</creator>

<item>
<rkts></rkts>
<ref>W01.01</ref>
<loc>Pander Pantheon I (1062). / Wanli Kanjur Supplement, vol. TA, fol. 1-300a5.</loc>
<tib>sngon 'gre gtor rna byin brlabs mdzad par zhu</tib>
<skttrans></skttrans>
<coloph></coloph>
<note></note>
</item>

<item>
<rkts></rkts>
<ref>W02.01</ref>
<loc>Pander Pantheon 2 (1063). / Wanli Kanjur Supplement, vol. PHA, Fol. 1-300b6.</loc>
<tib>phyogs dus kun khyab skyabs gsum bka' bstod bcas </tib>
<skttrans></skttrans>
<coloph></coloph>
<note></note>
</item>

<item>
<rkts></rkts>
<ref>W03.01</ref>
<loc>Pander Pantheon 3 (1064). / Wanli Kanjur Supplement, vol. NYA, Fol. 1-300a5.</loc>
<tib>sngon 'gro tor ma byin brlabs mdzad par zhu </tib>
<skttrans></skttrans>
<coloph></coloph>
<note></note>
</item>

<item>
<rkts></rkts>
<ref>W04.01</ref>
<loc>Pander Pantheon 4 (1065). / Wanli Kanjur Supplement, vol. DZA, fol. 1-312b6.</loc>
<tib>tshe dpag med lha dgu'i dkyil 'khor bzhugs sho // sngon 'gro gtor ma byin brlabs mdzad ba zhu </tib>
<skttrans></skttrans>
<coloph></coloph>
<note></note>
</item>

<item>
<rkts></rkts>
<ref>W05.01</ref>
<loc>Pander Pantheon 5 (1066). / Wanli Kanjur Supplement, vol. KE, Fol. 1-300a6.</loc>
<tib>mchod pa bsang sbyangs byin brlabs mdzad par zhu</tib>
<skttrans></skttrans>
<coloph></coloph>
<note></note>
</item>

<item>
<rkts></rkts>
<ref>W06.01</ref>
<loc>Pander Pantheon 6 (1067). / Wanli Kanjur Supplement, vol. NA, fol. 1-300b (incomplete at the end).</loc>
<tib></tib>
<skttrans></skttrans>
<coloph></coloph>
<note></note>
</item>

<item>
<rkts>554</rkts>
<ref>W07.01</ref>
<loc>Pander Pantheon 7 (1068). / Wanli Kanjur Supplement, vol. CHA, fol. 1-295a6.</loc>
<tib>rig sngags kyi rgyal mo rma bya chen mo chos</tib>
<skttrans></skttrans>
<coloph></coloph>
<note></note>
</item>

<item>
<rkts></rkts>
<ref>W08.01</ref>
<loc>Pander Pantheon 8 (1069). / Wanli Kanjur Supplement, vol. TSHA, fol. 1-300b6.</loc>
<tib>dpal rdo rje 'jigs byed bdag bskyed bzhugs sho </tib>
<skttrans></skttrans>
<coloph></coloph>
<note></note>
</item>

<item>
<rkts></rkts>
<ref>W09.01</ref>
<loc>Pander Pantheon 9 (1070). / Wanli Kanjur Supplement, vol. KA, Fol. 1-300b3.</loc>
<tib></tib>
<skttrans></skttrans>
<coloph></coloph>
<note></note>
</item>

<item>
<rkts></rkts>
<ref>W10.01</ref>
<loc>Pander Pantheon 10 (1071). / Wanli Kanjur Supplement, vol. ZA, Fol. 1-300b6.</loc>
<tib></tib>
<skttrans></skttrans>
<coloph></coloph>
<note></note>
</item>

<item>
<rkts></rkts>
<ref>W11.01</ref>
<loc>Pander Pantheon 11 (1072). / Wanli Kanjur Supplement, vol. SA, Fol. 1-281b6.</loc>
<tib>sngon 'gro'i gtor ma byin brla mdzad par zhu </tib>
<skttrans></skttrans>
<coloph></coloph>
<note></note>
</item>

<item>
<rkts></rkts>
<ref>W12.01</ref>
<loc>Pander Pantheon 12 (1073). / Wanli Kanjur Supplement, vol. JA, Fol. 1-300b6.</loc>
<tib>bsrungs 'khor mi' i rgyal po rndo bzhugs sho</tib>
<skttrans></skttrans>
<coloph></coloph>
<note></note>
</item>

<item>
<rkts>360</rkts>
<ref>W13.01</ref>
<loc>Pander Pantheon 13 (1074). / Wanli Kanjur Supplement, vol. KHI, Fol. 1-302b6.</loc>
<tib>'phags pa 'jam dpal gyi mtshan yang dag par brjod pa</tib>
<skttrans></skttrans>
<coloph></coloph>
<note></note>
</item>

<item>
<rkts></rkts>
<ref>W14.01</ref>
<loc>Pander Pantheon 14 (1075). / Wanli Kanjur Supplement, vol. YA, Fol. 1-301b6.</loc>
<tib></tib>
<skttrans></skttrans>
<coloph></coloph>
<note></note>
</item>

<item>
<rkts></rkts>
<ref>W15.01</ref>
<loc>Pander Pantheon I5 (1076). / Wanli Kanjur Supplement, vol. CA, Fol. 1-286b4.</loc>
<tib>sngon 'gro gtor ma'i byin rlab mdzad par zhu </tib>
<skttrans></skttrans>
<coloph></coloph>
<note></note>
</item>

<item>
<rkts>940</rkts>
<ref>W15.02</ref>
<loc>Pander Pantheon I5 (1076). / Wanli Kanjur Supplement, vol. CA, Fol. 286b4-305b5.</loc>
<tib>mdzad pa bcu gnyis kyi tshul la bstod pa zhes bya ba</tib>
<skttrans></skttrans>
<coloph></coloph>
<note></note>
</item>

<item>
<rkts></rkts>
<ref>W16.01</ref>
<loc>Pander Pantheon 16 (1077). / Wanli Kanjur Supplement, vol. Am, Fol. 1-211a5.</loc>
<tib></tib>
<skttrans></skttrans>
<coloph></coloph>
<note></note>
</item>

<item>
<rkts>529</rkts>
<ref>W16.02</ref>
<loc>Pander Pantheon 16 (1077). / Wanli Kanjur Supplement, vol. Am, Fol. 211a5-296b6.</loc>
<tib>bcom ldan 'das ma shes rab kyi pha rol du phyin pa'i snying po'o</tib>
<skttrans></skttrans>
<coloph></coloph>
<note></note>
</item>

<item>
<rkts></rkts>
<ref>W17.01</ref>
<loc>Pander Pantheon 17 (1078). / Wanli Kanjur Supplement, vol. Kau, Fol. 1-301b6.</loc>
<tib>sngon 'gro gtor ma byin brlabs mdzad bar zhu</tib>
<skttrans></skttrans>
<coloph></coloph>
<note></note>
</item>

<item>
<rkts></rkts>
<ref>W18.01</ref>
<loc>Pander Pantheon 18 (1079). / Wanli Kanjur Supplement, vol. Ah, Fol. 1-294b6.</loc>
<tib></tib>
<skttrans></skttrans>
<coloph></coloph>
<note></note>
</item>

<item>
<rkts>115</rkts>
<ref>W19.01</ref>
<loc>Pander Pantheon 19 (1080). / Wanli Kanjur Supplement, vol. HA, Fol. 1-300b6.</loc>
<tib>'phags pa bde ba can gyi bkod pa zhes bya ba theg pa chen po'i mdo</tib>
<skttrans></skttrans>
<coloph></coloph>
<note></note>
</item>

<item>
<rkts></rkts>
<ref>W20.01</ref>
<loc>Pander Pantheon 20 (1081). / Wanli Kanjur Supplement, vol. ZHA, Fol. 1-301b6.</loc>
<tib></tib>
<skttrans></skttrans>
<coloph></coloph>
<note></note>
</item>

<item>
<rkts></rkts>
<ref>W21.01</ref>
<loc>Pander Pantheon 21 (1082). / Wanli Kanjur Supplement, vol. Kam, Fol. 1-302b6.</loc>
<tib></tib>
<skttrans></skttrans>
<coloph></coloph>
<note></note>
</item>

<item>
<rkts></rkts>
<ref>W22.01</ref>
<loc>Pander Pantheon 22 (1083). / Wanli Kanjur Supplement, vol. RA, Fol. 1-300b6.</loc>
<tib></tib>
<skttrans></skttrans>
<coloph></coloph>
<note></note>
</item>

<item>
<rkts>360</rkts>
<ref>W23.01</ref>
<loc>Pander Pantheon 23 (1084). / Wanli Kanjur, rgyud, vol. KA, Fol. 1-15b</loc>
<tib>'jam dpal ye shes sems dpa'i don dam pa'i mtshan yang dag par brjod pa</tib>
<skttrans></skttrans>
<coloph></coloph>
<note></note>
</item>

<item>
<rkts>361</rkts>
<ref>W23.02</ref>
<loc>Pander Pantheon 23 (1084). / Wanli Kanjur, rgyud, vol. KA, Fol. 15b-23a</loc>
<tib>dbang mdor bstan pa</tib>
<skttrans></skttrans>
<coloph></coloph>
<note></note>
</item>

<item>
<rkts>362</rkts>
<ref>W23.03</ref>
<loc>Pander Pantheon 23 (1084). / Wanli Kanjur, rgyud, vol. KA, Fol.23b-141b8</loc>
<tib>mchog gi dang po'i sangs rgyas las phyung ba rgyud kyi rgyal po dpal dus kyi 'khor lo zhes bya ba</tib>
<skttrans></skttrans>
<coloph></coloph>
<note></note>
</item>

<item>
<rkts>363</rkts>
<ref>W23.04</ref>
<loc>Pander Pantheon 23 (1084). / Wanli Kanjur, rgyud, vol. KA, Fol. 141b8-158a2</loc>
<tib>dpal dus kyi 'khor lo'i rgyud phyi ma rgyud kyi snying po</tib>
<skttrans></skttrans>
<coloph></coloph>
<note></note>
</item>

<item>
<rkts>364</rkts>
<ref>W23.05</ref>
<loc>Pander Pantheon 23 (1084). / Wanli Kanjur, rgyud, vol. KA, Fol. 158a2-160a1</loc>
<tib>dpal dus kyi 'khor lo zhes bya ba'i rgyud kyi snying po</tib>
<skttrans></skttrans>
<coloph></coloph>
<note></note>
</item>

<item>
<rkts>365</rkts>
<ref>W23.06</ref>
<loc>Pander Pantheon 23 (1084). / Wanli Kanjur, rgyud, vol. KA, Fol. 160a1-164a5</loc>
<tib>dbang gi rab tu byed pa</tib>
<skttrans></skttrans>
<coloph></coloph>
<note></note>
</item>

<item>
<rkts>366</rkts>
<ref>W23.07</ref>
<loc>Pander Pantheon 23 (1084). / Wanli Kanjur, rgyud, vol. KA, Fol. 164a5-209a2</loc>
<tib>dpal sangs rgyas thams cad dang mnyam par sbyor ba mkha' 'gro ma sgyu ma bde ba'i mchog ces bya ba'i rgyud bla ma</tib>
<skttrans></skttrans>
<coloph></coloph>
<note></note>
</item>

<item>
<rkts>367</rkts>
<ref>W23.08</ref>
<loc>Pander Pantheon 23 (1084). / Wanli Kanjur, rgyud, vol. KA, Fol. 209a2-230a3</loc>
<tib>rtog pa thams cad 'dus pa zhes bya ba sangs rgyas thams cad dang mnyam bar sbyor ba mkha' 'gro sgyu ma bde ba'i mchog gi rgyud phyi ma</tib>
<skttrans></skttrans>
<coloph></coloph>
<note></note>
</item>

<item>
<rkts>417</rkts>
<ref>W23.09</ref>
<loc>Pander Pantheon 23 (1084). / Wanli Kanjur, rgyud, vol. KA, Fol. 230a3-262a5</loc>
<tib>kye'i rdo rje zhes bya ba rgyud kyi rgyal po</tib>
<skttrans></skttrans>
<coloph></coloph>
<note></note>
</item>

<item>
<rkts>419</rkts>
<ref>W23.10</ref>
<loc>Pander Pantheon 23 (1084). / Wanli Kanjur, rgyud, vol. KA, Fol. 262a5-301b4</loc>
<tib>'phags pa mkha' 'gro ma rdo rje gur zhes bya ba'i rgyud kyi rgyal po chen po'i brtag pa</tib>
<skttrans></skttrans>
<coloph></coloph>
<note></note>
</item>

<item>
<rkts>420</rkts>
<ref>W23.11</ref>
<loc>Pander Pantheon 23 (1084). / Wanli Kanjur, rgyud, vol. KA, Fol. 301b4-329a6</loc>
<tib>dpal phyag rgya chen po'i thig Ie zhes bya ba rnal 'byor ma chen mo'i rgyud kyi rgyal po'i mnga' bdag</tib>
<skttrans></skttrans>
<coloph></coloph>
<note></note>
</item>

<item>
<rkts>383</rkts>
<ref>W24.01</ref>
<loc>Pander Pantheon 24 (1085). / Wanli Kanjur, rgyud, vol. NGA, fol. 1-4a8.</loc>
<tib>dpal gsang ba rdo rje rgyud kyi rgyal po dpal rdo rje mkha' 'gro la phyag 'tshal lo</tib>
<skttrans></skttrans>
<coloph></coloph>
<note></note>
</item>

<item>
<rkts>384</rkts>
<ref>W24.02</ref>
<loc>Pander Pantheon 24 (1085). / Wanli Kanjur, rgyud, vol. NGA, fol. 4a8-13a2.</loc>
<tib>dpal gsang ba thams cad gcod pa'i rgyud kyi rgyal po</tib>
<skttrans></skttrans>
<coloph></coloph>
<note></note>
</item>

<item>
<rkts>385</rkts>
<ref>W24.03</ref>
<loc>Pander Pantheon 24 (1085). / Wanli Kanjur, rgyud, vol. NGA, fol. 13a2-16b4.</loc>
<tib>dpal 'khor lo sdom ba'i gsang ba bsam gyis mi khyab pa'i rgyud kyi rgyal po</tib>
<skttrans></skttrans>
<coloph></coloph>
<note></note>
</item>

<item>
<rkts>386</rkts>
<ref>W24.04</ref>
<loc>Pander Pantheon 24 (1085). / Wanli Kanjur, rgyud, vol. NGA, fol. 16b4-19a7.</loc>
<tib>dpal nam mkha' dang mnyam pa'i rgyud kyi rgyal po zhes bya ba dpal bde mchog la phyag 'tshal lo</tib>
<skttrans></skttrans>
<coloph></coloph>
<note></note>
</item>

<item>
<rkts>387</rkts>
<ref>W24.05</ref>
<loc>Pander Pantheon 24 (1085). / Wanli Kanjur, rgyud, vol. NGA, fol. 19a7-20b7.</loc>
<tib>dpal nam mkha 'chen po'i rgyud kyi rgyal po</tib>
<skttrans></skttrans>
<coloph></coloph>
<note></note>
</item>

<item>
<rkts>388</rkts>
<ref>W24.06</ref>
<loc>Pander Pantheon 24 (1085). / Wanli Kanjur, rgyud, vol. NGA, fol. 20b7-25b8.</loc>
<tib>dpal sku gsung thugs kyi rgyud kyi rgyal po</tib>
<skttrans></skttrans>
<coloph></coloph>
<note></note>
</item>

<item>
<rkts>389</rkts>
<ref>W24.07</ref>
<loc>Pander Pantheon 24 (1085). / Wanli Kanjur, rgyud, vol. NGA, fol. 26a1-31a6.</loc>
<tib>dpal rin chen phreng ba'i rgyud kyi rgyal po</tib>
<skttrans></skttrans>
<coloph></coloph>
<note></note>
</item>

<item>
<rkts>390</rkts>
<ref>W24.08</ref>
<loc>Pander Pantheon 24 (1085). / Wanli Kanjur, rgyud, vol. NGA, fol. 31a6-33b6.</loc>
<tib>dpal dam tshig chen po'i rgyud kyi rgyal po zhes bya ba</tib>
<skttrans></skttrans>
<coloph></coloph>
<note></note>
</item>

<item>
<rkts>391</rkts>
<ref>W24.09</ref>
<loc>Pander Pantheon 24 (1085). / Wanli Kanjur, rgyud, vol. NGA, fol. 33b6-36b5.</loc>
<tib>dpal stabs po che'i rgyud kyi rgyal po zhes bya ba</tib>
<skttrans></skttrans>
<coloph></coloph>
<note></note>
</item>

<item>
<rkts>392</rkts>
<ref>W24.10</ref>
<loc>Pander Pantheon 24 (1085). / Wanli Kanjur, rgyud, vol. NGA, fol. 36b6-38a5.</loc>
<tib>dpal ye shes gsang ba'i rgyud kyi rgyal po</tib>
<skttrans></skttrans>
<coloph></coloph>
<note></note>
</item>

<item>
<rkts>393</rkts>
<ref>W24.11</ref>
<loc>Pander Pantheon 24 (1085). / Wanli Kanjur, rgyud, vol. NGA, fol. 38a5-39b5.</loc>
<tib>dpal ye shes phreng ba'i rgyud kyi rgyal po</tib>
<skttrans></skttrans>
<coloph></coloph>
<note></note>
</item>

<item>
<rkts>394</rkts>
<ref>W24.12</ref>
<loc>Pander Pantheon 24 (1085). / Wanli Kanjur, rgyud, vol. NGA, fol. 39b5-41a5.</loc>
<tib>dpal ye shes 'bar ba'i rgyud kyi rgyal po</tib>
<skttrans></skttrans>
<coloph></coloph>
<note></note>
</item>

<item>
<rkts>395</rkts>
<ref>W24.13</ref>
<loc>Pander Pantheon 24 (1085). / Wanli Kanjur, rgyud, vol. NGA, fol. 41a5-42b3.</loc>
<tib>dpal zla ba'i phreng ba'i rgyud kyi rgyal po</tib>
<skttrans></skttrans>
<coloph></coloph>
<note></note>
</item>

<item>
<rkts>396</rkts>
<ref>W24.14</ref>
<loc>Pander Pantheon 24 (1085). / Wanli Kanjur, rgyud, vol. NGA, fol. 42b3-45b4.</loc>
<tib>dpal rin chen 'bar ba'i rgyud kyi rgyal po zhes bya ba</tib>
<skttrans></skttrans>
<coloph></coloph>
<note></note>
</item>

<item>
<rkts>397</rkts>
<ref>W24.15</ref>
<loc>Pander Pantheon 24 (1085). / Wanli Kanjur, rgyud, vol. NGA, fol. 45b4-47a4.</loc>
<tib>dpal nyi ma'i 'khor lo'i rgyud kyi rgyal po zhes bya ba</tib>
<skttrans></skttrans>
<coloph></coloph>
<note></note>
</item>

<item>
<rkts>398</rkts>
<ref>W24.16</ref>
<loc>Pander Pantheon 24 (1085). / Wanli Kanjur, rgyud, vol. NGA, fol. 47a4-48a6.</loc>
<tib>dpal ye shes rgyal po'i rgyud kyi rgyal po</tib>
<skttrans></skttrans>
<coloph></coloph>
<note></note>
</item>

<item>
<rkts>399</rkts>
<ref>W24.17</ref>
<loc>Pander Pantheon 24 (1085). / Wanli Kanjur, rgyud, vol. NGA, fol. 48a6-50a1.</loc>
<tib>dpal rdo rje mkha' 'gro gsang ba'i rgyud kyi rgyal po</tib>
<skttrans></skttrans>
<coloph></coloph>
<note></note>
</item>

<item>
<rkts>400</rkts>
<ref>W24.18</ref>
<loc>Pander Pantheon 24 (1085). / Wanli Kanjur, rgyud, vol. NGA, fol. 50a1-51b6.</loc>
<tib>dpal gsang ba me 'bar ba'i rgyud kyi rgyal po</tib>
<skttrans></skttrans>
<coloph></coloph>
<note></note>
</item>

<item>
<rkts>401</rkts>
<ref>W24.19</ref>
<loc>Pander Pantheon 24 (1085). / Wanli Kanjur, rgyud, vol. NGA, fol. 51b6-53b8.</loc>
<tib>dpal gsang ba bdud rtsi'i rgyud kyi rgyal po</tib>
<skttrans></skttrans>
<coloph></coloph>
<note></note>
</item>

<item>
<rkts>402</rkts>
<ref>W24.20</ref>
<loc>Pander Pantheon 24 (1085). / Wanli Kanjur, rgyud, vol. NGA, fol. 53b8-55b8.</loc>
<tib>dpal dur khrod rgyan gyi rgyud gyi rgyal po</tib>
<skttrans></skttrans>
<coloph></coloph>
<note></note>
</item>

<item>
<rkts>403</rkts>
<ref>W24.21</ref>
<loc>Pander Pantheon 24 (1085). / Wanli Kanjur, rgyud, vol. NGA, fol. 56a1-57b4.</loc>
<tib>dpal rdo rje rgyal po chen po'i rgyud</tib>
<skttrans></skttrans>
<coloph></coloph>
<note></note>
</item>

<item>
<rkts>404</rkts>
<ref>W24.22</ref>
<loc>Pander Pantheon 24 (1085). / Wanli Kanjur, rgyud, vol. NGA, fol. 57b4-58b5.</loc>
<tib>dpal ye shes bsam ba'i rgyud kyi rgyal po</tib>
<skttrans></skttrans>
<coloph></coloph>
<note></note>
</item>

<item>
<rkts>405</rkts>
<ref>W24.23</ref>
<loc>Pander Pantheon 24 (1085). / Wanli Kanjur, rgyud, vol. NGA, fol. 58b5-62a4.</loc>
<tib>dpal chags pa i rgyal po'i rgyud kyi rgyal po</tib>
<skttrans></skttrans>
<coloph></coloph>
<note></note>
</item>

<item>
<rkts>406</rkts>
<ref>W24.24</ref>
<loc>Pander Pantheon 24 (1085). / Wanli Kanjur, rgyud, vol. NGA, fol. 62a4-63b8.</loc>
<tib>dpal mkha' 'gro ma'i sdom ba'i rgyud kyi rgyal po zhes bya ba</tib>
<skttrans></skttrans>
<coloph></coloph>
<note></note>
</item>

<item>
<rkts>408</rkts>
<ref>W24.25</ref>
<loc>Pander Pantheon 24 (1085). / Wanli Kanjur, rgyud, vol. NGA, fol. 63b8-65a8.</loc>
<tib>dpal mkha' 'gro ma gsang ba 'bar ba'i rgyud kyi rgyal po</tib>
<skttrans></skttrans>
<coloph></coloph>
<note></note>
</item>

<item>
<rkts>409</rkts>
<ref>W24.26</ref>
<loc>Pander Pantheon 24 (1085). / Wanli Kanjur, rgyud, vol. NGA, fol. 65a8-66a7.</loc>
<tib>dpal rdo rje 'jigs byed rnam par 'joms pa'i rgyud kyi rgyal po</tib>
<skttrans></skttrans>
<coloph></coloph>
<note></note>
</item>

<item>
<rkts>407</rkts>
<ref>W24.27</ref>
<loc>Pander Pantheon 24 (1085). / Wanli Kanjur, rgyud, vol. NGA, fol. 66a7-67b8.</loc>
<tib>dpal me'i phreng ba'i rgyud kyi rgyal po</tib>
<skttrans></skttrans>
<coloph></coloph>
<note></note>
</item>

<item>
<rkts>411</rkts>
<ref>W24.28</ref>
<loc>Pander Pantheon 24 (1085). / Wanli Kanjur, rgyud, vol. NGA, fol. 68a1-70a1.</loc>
<tib>dpal rdo rje grub pa dra ba'i sdom pa'i rgyud kyi rgyal po</tib>
<skttrans></skttrans>
<coloph></coloph>
<note></note>
</item>

<item>
<rkts>410</rkts>
<ref>W24.29</ref>
<loc>Pander Pantheon 24 (1085). / Wanli Kanjur, rgyud, vol. NGA, fol. 70a1-71b8.</loc>
<tib>dpal stobs chen ye shes rgyal po'i rgyud kyi rgyal po</tib>
<skttrans></skttrans>
<coloph></coloph>
<note></note>
</item>

<item>
<rkts>413</rkts>
<ref>W24.30</ref>
<loc>Pander Pantheon 24 (1085). / Wanli Kanjur, rgyud, vol. NGA, fol. 72a1-77b6.</loc>
<tib>dpal 'khor sdom pa'i rgyud kyi rgyal po dur khrod kyi rgyan rmad du byung ba zhes bya ba</tib>
<skttrans></skttrans>
<coloph></coloph>
<note></note>
</item>

<item>
<rkts>414</rkts>
<ref>W24.31</ref>
<loc>Pander Pantheon 24 (1085). / Wanli Kanjur, rgyud, vol. NGA, fol. 77b6-80a3.</loc>
<tib>rgyud kyi rgyal po rnyog pa med pa zhes bya ba</tib>
<skttrans></skttrans>
<coloph></coloph>
<note></note>
</item>

<item>
<rkts>415</rkts>
<ref>W24.32</ref>
<loc>Pander Pantheon 24 (1085). / Wanli Kanjur, rgyud, vol. NGA, fol. 80a3-82a6.</loc>
<tib>dpal bde mchog nam mkha' dang mnyam pa'i rgyud kyi rgyal po zhes bya ba</tib>
<skttrans></skttrans>
<coloph></coloph>
<note></note>
</item>

<item>
<rkts>378</rkts>
<ref>W24.33</ref>
<loc>Pander Pantheon 24 (1085). / Wanli Kanjur, rgyud, vol. NGA, fol. 82a8-95a2.</loc>
<tib>mkha' 'gro ma thams cad kyi thugs gnyis su med pa bsam gyis mi khyab pa'i ye shes rdo rje phag mo mngon par 'byung ba'i rgyud kyi rgyal po zhes bya ba</tib>
<skttrans></skttrans>
<coloph></coloph>
<note></note>
</item>

<item>
<rkts>416</rkts>
<ref>W24.34</ref>
<loc>Pander Pantheon 24 (1085). / Wanli Kanjur, rgyud, vol. NGA, fol. 95a2-126b4.</loc>
<tib>dpal rdo rje nag po chen po khros pa'i mgon po gsang ba dngos grub 'byung ba zhes bya ba'i rgyud</tib>
<skttrans></skttrans>
<coloph></coloph>
<note></note>
</item>

<item>
<rkts>424</rkts>
<ref>W24.35</ref>
<loc>Pander Pantheon 24 (1085). / Wanli Kanjur, rgyud, vol. NGA, fol. 126b4-153a6.</loc>
<tib>dpal sangs rgyas thong ba zhes bya ba rnal 'byor ma'i rgyud kyi rgyal po</tib>
<skttrans></skttrans>
<coloph></coloph>
<note></note>
</item>

<item>
<rkts>425</rkts>
<ref>W24.36</ref>
<loc>Pander Pantheon 24 (1085). / Wanli Kanjur, rgyud, vol. NGA, fol. 153a6-157a4.</loc>
<tib>sgyu 'phrul chen po'i rgyud ces bya ba</tib>
<skttrans></skttrans>
<coloph></coloph>
<note></note>
</item>

<item>
<rkts>426</rkts>
<ref>W24.37</ref>
<loc>Pander Pantheon 24 (1085). / Wanli Kanjur, rgyud, vol. NGA, fol. 157a4-162a3.</loc>
<tib>rdo rje a ra li zhes bya ba'i rgyud kyi rgyal po chen po</tib>
<skttrans></skttrans>
<coloph></coloph>
<note></note>
</item>

<item>
<rkts>427</rkts>
<ref>W24.38</ref>
<loc>Pander Pantheon 24 (1085). / Wanli Kanjur, rgyud, vol. NGA, fol. 162a3-167a8.</loc>
<tib>ri gi a ra li'i rgyud kyi rgyal po zhes bya ba</tib>
<skttrans></skttrans>
<coloph></coloph>
<note></note>
</item>

<item>
<rkts>428</rkts>
<ref>W24.39</ref>
<loc>Pander Pantheon 24 (1085). / Wanli Kanjur, rgyud, vol. NGA, fol. 167a8-217a2.</loc>
<tib>rnal 'byor ma'i rgyud kyi rgyal po chen po dpal gdan bzhi pa zhes bya ba</tib>
<skttrans></skttrans>
<coloph></coloph>
<note></note>
</item>

<item>
<rkts></rkts>
<ref>W24.40</ref>
<loc>Pander Pantheon 24 (1085). / Wanli Kanjur, rgyud, vol. NGA, fol. 217a2-217a7.</loc>
<tib></tib>
<skttrans></skttrans>
<coloph></coloph>
<note></note>
</item>

<item>
<rkts></rkts>
<ref>W24.41</ref>
<loc>Pander Pantheon 24 (1085). / Wanli Kanjur, rgyud, vol. NGA, fol. 217a7-271a6.</loc>
<tib></tib>
<skttrans></skttrans>
<coloph></coloph>
<note></note>
</item>

<item>
<rkts></rkts>
<ref>W24.42</ref>
<loc>Pander Pantheon 24 (1085). / Wanli Kanjur, rgyud, vol. NGA, fol. 271a6-282b2.</loc>
<tib></tib>
<skttrans></skttrans>
<coloph></coloph>
<note></note>
</item>

<item>
<rkts></rkts>
<ref>W24.43</ref>
<loc>Pander Pantheon 24 (1085). / Wanli Kanjur, rgyud, vol. NGA, fol. 282b2-288a4.</loc>
<tib></tib>
<skttrans></skttrans>
<coloph></coloph>
<note></note>
</item>

<item>
<rkts>431</rkts>
<ref>W24.44</ref>
<loc>Pander Pantheon 24 (1085). / Wanli Kanjur, rgyud, vol. NGA, fol. 288a4-330a4.</loc>
<tib>dpal gtum po khro bo chen po'i rgyud kyi rgyal po zhes bya ba</tib>
<skttrans></skttrans>
<coloph></coloph>
<note></note>
</item>

<item>
<rkts>452</rkts>
<ref>W25.01</ref>
<loc>Pander Pantheon 25 (1086). / Wanli Kanjur, rgyud, vol. CHA, fol. 1a1-42b2.</loc>
<tib>-</tib>
<skttrans></skttrans>
<coloph>'phags pa gnyis su med pa mnyam ba nyid rnam par rgyal ba zhes bya ba'i rtog pa 'i rgyal po chen po rdzogs so [s.ho] // mkhan chen thar ba lo tstsha ba'i phyag dpe'i gseb nas shog yar lnga byung bsngar bsgyur ba las // phyis nyan stong smon gro'i gtsug lag khang nas rgya dpe lhag rna rnams rnyed nas bsgyur bar rtsom ba na / dpal dus kyi 'khor lo'i phyi nang gzhan gsum gyis tshul la mi 'jigs pa'i spobs pa thob ba'i bla ma yang dag pa'i dge ba'i bshes gnyen chen po legs par sbyar pa'i skad kyi brda sprod pa'i tshul la blo gros shin tu byang ba'i 'jig rten gyi mig chos grags dpal bzang po'i bkas bskul zhing sbyin bdag mdzad nas // bu ston gyis bsgyur ba'i I yi ge pa ni dge slong rin chen rgyal mtshan no</coloph>
<note></note>
</item>

<item>
<rkts>453</rkts>
<ref>W25.02</ref>
<loc>Pander Pantheon 25 (1086). / Wanli Kanjur, rgyud, vol. CHA, fol. 43a1-281b8.</loc>
<tib>dpal de bzhin gshegs pa thams cad kyi gsang ba rnal 'byor chen po rnam par rgyal ba zhes bya ba mnyam ba gnyis su med pa'i rgyud kyi rgyal po rdo rje dpal mchog chen po brtag pa dang po</tib>
<skttrans></skttrans>
<coloph>rgya gar gyi mkhan po dpal ye shes snying po dang // bod kyi lo tstsha ba mar ba lho brag pa chos kyi blo gros kyis bsgyur cing zhus te gtan la phab pa'o // pan di ta mkhas pa chen po smri ti [gi gu] jna na kir tis rang 'gyur byas pa cig kyang yod bar gda'o</coloph>
<note></note>
</item>

<item>
<rkts>454</rkts>
<ref>W25.03</ref>
<loc>Pander Pantheon 25 (1086). / Wanli Kanjur, rgyud, vol. CHA, fol. 282a3-283b7.</loc>
<tib>'phags pa lag na rdo rje gos sngon bo can drag bo gsum 'dul ba zhes bya ba'i rgyud</tib>
<skttrans></skttrans>
<coloph></coloph>
<note></note>
</item>

<item>
<rkts>455</rkts>
<ref>W25.04</ref>
<loc>Pander Pantheon 25 (1086). / Wanli Kanjur, rgyud, vol. CHA, fol. 283b7-288a6.</loc>
<tib>gsang ba'i rgyud rnams kyi rnam par 'byed pa drag po gsum 'dul zhesbya ba</tib>
<skttrans></skttrans>
<coloph></coloph>
<note></note>
</item>

<item>
<rkts>456</rkts>
<ref>W25.05</ref>
<loc>Pander Pantheon 25 (1086). / Wanli Kanjur, rgyud, vol. CHA, fol. 288a7-292a8.</loc>
<tib>lag na rdo rje gos sngon po can gyi cho ga rdo rje be con gyi rgyud</tib>
<skttrans></skttrans>
<coloph>'phags pa lag na rdo rje gos sngon po can gyi cho ga rdo rje be con gyi rgyud rdzogs so</coloph>
<note></note>
</item>

<item>
<rkts>457</rkts>
<ref>W25.06</ref>
<loc>Pander Pantheon 25 (1086). / Wanli Kanjur, rgyud, vol. CHA, fol. 292a8-295a5.</loc>
<tib>bcom ldan 'das phyag na rdo rje gos sngon po can gyi rdo rje gdengs pa'i rgyud las khams gsum rnam par rgyal ba zhes bya ba'i le'u</tib>
<skttrans></skttrans>
<coloph>bcom ldan 'das phyag na rdo rje gos sngon po can gyi rdo rje gdengs pa'i rgyud las khams gsum rnam par rgyal ba zhes bya ba'i le'u rdzogsto // pan di ta a da ya srI ma ti zhes bya ba dang / bod kyi lo tstsha ba ban de chos kyi dbang phyug grags kyis bsgyur cing zhus te gtan la phab pa'o</coloph>
<note></note>
</item>

<item>
<rkts>458</rkts>
<ref>W25.07</ref>
<loc>Pander Pantheon 25 (1086). / Wanli Kanjur, rgyud, vol. CHA, fol. 295a6-310b1.</loc>
<tib>dpal rdo rje gtum po thugs gsang ba'i rgyud</tib>
<skttrans></skttrans>
<coloph>dpal rdo rje gtum po thugs gsang ba 'i rgyud las yongsu btad pa'i le'u ste nyi shu rtsa bzhi pa'o // // rgya gar gyi mkhan po a pa yu gha ta'i zhal snga nas zhus nas // bod kyi lo tstsha ba chos kyi brtson 'grus kyis bsgyur ba rdzogso</coloph>
<note></note>
</item>

<item>
<rkts>459</rkts>
<ref>W25.08</ref>
<loc>Pander Pantheon 25 (1086). / Wanli Kanjur, rgyud, vol. CHA, fol. 310b1-316b1.</loc>
<tib>dpal rdo rje gtum po thugs gsang ba'i rgyud phyi ma</tib>
<skttrans></skttrans>
<coloph>dpal rdo rje gtum po thugs gsang ba 'i rgyud phyi ma las dpal rdo rje gtum po thugs gsang ba'i rgyud phyi ma rdzogsto // // rgya gar gyi slob dpon a pa yu ga ti la dang / bod kyi lo tstsha ba bla ban chos kyi grtson bgrus kyis zhus te bsgyur cing gran la phab pa'o</coloph>
<note></note>
</item>

<item>
<rkts>460</rkts>
<ref>W25.09</ref>
<loc>Pander Pantheon 25 (1086). / Wanli Kanjur, rgyud, vol. CHA, fol. 316b1-320a1.</loc>
<tib></tib>
<skttrans></skttrans>
<coloph>dpal rdo rje gtum po thugs gsang ba'i rgyud phyi ma'i phyi ma rdzogs sto // // rgya gar gyi slob dpon a ba yu ga ti la dang / bod kyi lo tstsha ba bla ban chos kyi brtson 'grus kyis zhus te bsgyur cing gtan la phab pa'o</coloph>
<note></note>
</item>

<item>
<rkts>461</rkts>
<ref>W25.10</ref>
<loc></loc>
<tib>phyag na rdo rje gos sngon po can gnod sbyin drag po chen po rdo rje me lce'i rgyud ces bya ba</tib>
<skttrans></skttrans>
<coloph>Pander Pantheon 25 (1086). / Wanli Kanjur, rgyud, vol. CHA, fol. 320a1-.</coloph>
<note></note>
</item>

<item>
<rkts>495</rkts>
<ref>W26.01</ref>
<loc>Pander Pantheon 26 (1086). / Wanli Kanjur, rgyud, vol. DA, fol.1-</loc>
<tib>'phags pa lag na rdo rje dbang bskur ba'i rgyud chen po</tib>
<skttrans></skttrans>
<coloph></coloph>
<note></note>
</item>

<item>
<rkts>501</rkts>
<ref>W26.02</ref>
<loc>Pander Pantheon 26 (1086). / Wanli Kanjur, rgyud, vol. DA, fol.166a6-</loc>
<tib></tib>
<skttrans></skttrans>
<coloph></coloph>
<note></note>
</item>

<item>
<rkts>502</rkts>
<ref>W26.03</ref>
<loc>Pander Pantheon 26 (1086). / Wanli Kanjur, rgyud, vol. DA, fol.230a5-</loc>
<tib></tib>
<skttrans></skttrans>
<coloph></coloph>
<note></note>
</item>

<item>
<rkts>503</rkts>
<ref>W26.04</ref>
<loc>Pander Pantheon 26 (1086). / Wanli Kanjur, rgyud, vol. DA, fol.253b7-</loc>
<tib></tib>
<skttrans></skttrans>
<coloph></coloph>
<note></note>
</item>

<item>
<rkts>503</rkts>
<ref>W26.04</ref>
<loc>Pander Pantheon 26 (1086). / Wanli Kanjur, rgyud, vol. DA, fol.263a1-</loc>
<tib></tib>
<skttrans></skttrans>
<coloph></coloph>
<note></note>
</item>

<item>
<rkts>680</rkts>
<ref>W27.01</ref>
<loc>Pander Pantheon 27 (1088). / Wanli Kanjur, rgyud, vol. MA, fol.1b1-</loc>
<tib>'phags pa don yod pa'i zhags pa'i cho ga zhib mo'i rgyal po</tib>
<skttrans></skttrans>
<coloph></coloph>
<note></note>
</item>

<item>
<rkts>676</rkts>
<ref>W27.02</ref>
<loc>Pander Pantheon 27 (1088). / Wanli Kanjur, rgyud, vol. MA, fol.255b2-</loc>
<tib>'phags pa don yod zhags pa'i snying po zhes bya ba theg pa chen po 'i mdo</tib>
<skttrans></skttrans>
<coloph></coloph>
<note></note>
</item>

<item>
<rkts>681</rkts>
<ref>W27.03</ref>
<loc>Pander Pantheon 27 (1088). / Wanli Kanjur, rgyud, vol. MA, fol.261a7-</loc>
<tib></tib>
<skttrans></skttrans>
<coloph></coloph>
<note></note>
</item>

<item>
<rkts>910</rkts>
<ref>W27.04</ref>
<loc>Pander Pantheon 27 (1088). / Wanli Kanjur, rgyud, vol. MA, fol.263a4-</loc>
<tib>'phags pa spyan ras gzigs dbang phyug phyag stong spyan stong du sprul pa rgya chen po yongs su rdzogs pa thogs pa med par thugs rje chen po dang ldan pa'i gzungs</tib>
<skttrans></skttrans>
<coloph></coloph>
<note></note>
</item>

<item>
<rkts>685</rkts>
<ref>W27.05</ref>
<loc>Pander Pantheon 27 (1088). / Wanli Kanjur, rgyud, vol. MA, fol.270a6-</loc>
<tib>'phags pa byang chub sems dpa' spyan ras gzigs dbang phyug phyag stong...</tib>
<skttrans></skttrans>
<coloph></coloph>
<note></note>
</item>

<item>
<rkts>830</rkts>
<ref>W28.01</ref>
<loc>Pander Pantheon 28 (1089). / Wanli Kanjur, rgyud, vol. ZHA, fol.1b1-291</loc>
<tib>lha mo sgyu 'phrul dra ba chen mo zhes bya ba'i rgyud</tib>
<skttrans></skttrans>
<coloph></coloph>
<note></note>
</item>

<item>
<rkts>8</rkts>
<ref>W29.01</ref>
<loc>Pander Pantheon 29 (1090). </loc>
<tib></tib>
<skttrans></skttrans>
<coloph></coloph>
<note>(Not volume from Wanli Kanjur)</note>
</item>

<item>
<rkts>8</rkts>
<ref>W30.01</ref>
<loc>Pander Pantheon 30 (1091). / Wanli Kanjur, sher phyin, vol. CA, fol.1b1-339</loc>
<tib></tib>
<skttrans></skttrans>
<coloph></coloph>
<note></note>
</item>

<item>
<rkts>8</rkts>
<ref>W31.01</ref>
<loc>Pander Pantheon 31 (1092). / Wanli Kanjur, sher phyin, vol. CHA, fol.1b1-330</loc>
<tib></tib>
<skttrans></skttrans>
<coloph></coloph>
<note></note>
</item>

<item>
<rkts>8</rkts>
<ref>W32.01</ref>
<loc>Pander Pantheon 32 (1093). </loc>
<tib></tib>
<skttrans></skttrans>
<coloph></coloph>
<note>(Not volume from Wanli Kanjur)</note>
</item>

<item>
<rkts>8</rkts>
<ref>W33.01</ref>
<loc>Pander Pantheon 33 (1094). / Wanli Kanjur, sher phyin, vol. DA, fol.1b1-323</loc>
<tib></tib>
<skttrans></skttrans>
<coloph></coloph>
<note></note>
</item>

<item>
<rkts>8</rkts>
<ref>W34.01</ref>
<loc>Pander Pantheon 34 (1095). / Wanli Kanjur, sher phyin, vol. PA, fol.1b1-323</loc>
<tib></tib>
<skttrans></skttrans>
<coloph></coloph>
<note></note>
</item>

<item>
<rkts>8</rkts>
<ref>W35.01</ref>
<loc>Pander Pantheon 35 (1096). </loc>
<tib></tib>
<skttrans></skttrans>
<coloph></coloph>
<note>(Not volume from Wanli Kanjur)</note>
</item>

<item>
<rkts>8</rkts>
<ref>W36.01</ref>
<loc>Pander Pantheon 36 (1097). / Wanli Kanjur, sher phyin, vol. KA, fol.1b1-319</loc>
<tib></tib>
<skttrans></skttrans>
<coloph></coloph>
<note></note>
</item>

<item>
<rkts>8</rkts>
<ref>W37.01</ref>
<loc>Pander Pantheon 37 (1098). </loc>
<tib></tib>
<skttrans></skttrans>
<coloph></coloph>
<note>(Not volume from Wanli Kanjur)</note>
</item>

<item>
<rkts>372</rkts>
<ref>W38.01</ref>
<loc>Pander Pantheon 38 (1099). / Wanli Kanjur, rgyud, vol. GA, fol.1b1-357</loc>
<tib>dpal mkha' 'gro rgya mtsho chen po mal 'byor ma'i rgyud kyi rgyal po zhes bya ba</tib>
<skttrans></skttrans>
<coloph></coloph>
<note></note>
</item>

<item>
<rkts>421</rkts>
<ref>W39.01</ref>
<loc>Pander Pantheon 39 (1100). / Wanli Kanjur, rgyud, vol. KHA, fol.1b1-358</loc>
<tib>dpal ye shes snying po zhes bya ba rnal 'byor ma chen mo'i rgyud kyi rgyal po'i rgyal po</tib>
<skttrans></skttrans>
<coloph></coloph>
<note></note>
</item>

<item>
<rkts>432</rkts>
<ref>W40.01</ref>
<loc>Pander Pantheon 40 (1101). / Wanli Kanjur, rgyud, vol. CA, fol.1b1-320</loc>
<tib>'phags pa mi gyo ba'i rtog pa'i rgyud kyi rgyal po</tib>
<skttrans></skttrans>
<coloph></coloph>
<note></note>
</item>

<item>
<rkts>489</rkts>
<ref>W41.01</ref>
<loc>Pander Pantheon 41 (1102). / Wanli Kanjur, rgyud, vol. TA, fol.1b1-304</loc>
<tib>dpal rdo rje snying po rgyan ces bya ba'i rgyud kyi rgyal po chen po</tib>
<skttrans></skttrans>
<coloph></coloph>
<note></note>
</item>

<item>
<rkts>482</rkts>
<ref>W42.01</ref>
<loc>Pander Pantheon 42 (1103). / Wanli Kanjur, rgyud, vol. TA, fol.1b1-323</loc>
<tib>'jig rten gsum las rnam par rgyal bar tog pa'i rgyal po chen po</tib>
<skttrans></skttrans>
<coloph></coloph>
<note></note>
</item>

<item>
<rkts>479</rkts>
<ref>W43.01</ref>
<loc>Pander Pantheon 43 (1104). / Wanli Kanjur, rgyud, vol. NYA, fol.1b1-311</loc>
<tib>de bzhin gshegs pa thams cad kyi de kho na nyid bsdus pa zhes bya ba theg pa chen po'i mdo</tib>
<skttrans></skttrans>
<coloph></coloph>
<note></note>
</item>

<item>
<rkts>461</rkts>
<ref>W44.01</ref>
<loc>Pander Pantheon 44 (1105). / Wanli Kanjur, rgyud, vol. JA, fol.1b1-311</loc>
<tib>phyag na rdo rje gos sngon po can gnod sbyin drag po chen po rdo rje me lce'i rgyud ces bya ba</tib>
<skttrans></skttrans>
<coloph></coloph>
<note></note>
</item>

<item>
<rkts>536</rkts>
<ref>W45.01</ref>
<loc>Pander Pantheon 45 (1106). / Wanli Kanjur, rgyud, vol. BA, fol.1b1-310</loc>
<tib>mchod pa'i sprin zhes bya ba'i gzungs</tib>
<skttrans></skttrans>
<coloph></coloph>
<note></note>
</item>

<item>
<rkts></rkts>
<ref>W46.01</ref>
<loc>Pander Pantheon 46 (1107). / Wanli Kanjur, rgyud, vol. Za, fol.1b1-285</loc>
<tib></tib>
<skttrans></skttrans>
<coloph></coloph>
<note></note>
</item>

<item>
<rkts>8</rkts>
<ref>W47.01</ref>
<loc>Pander Pantheon 47 (1108). / Wanli Kanjur, yum, vol. NYA, fol.1b1-367</loc>
<tib></tib>
<skttrans></skttrans>
<coloph></coloph>
<note></note>
</item>

<item>
<rkts>847</rkts>
<ref>W48.01</ref>
<loc>Pander Pantheon 48 (1109). / Wanli Kanjur, rgyud, vol. 'A, fol.1b1-279</loc>
<tib>spyan 'dren rgyud gsum pa</tib>
<skttrans></skttrans>
<coloph></coloph>
<note></note>
</item>

<item>
<rkts>8</rkts>
<ref>W49.01</ref>
<loc>Pander Pantheon 49 (1110). / Wanli Kanjur, yum, vol. NA, fol.1b1-367</loc>
<tib></tib>
<skttrans></skttrans>
<coloph></coloph>
<note></note>
</item>

<item>
<rkts>745</rkts>
<ref>W50.01</ref>
<loc>Pander Pantheon 50 (1111). / Wanli Kanjur, rgyud, vol. YA, fol.1b1-33b6</loc>
<tib>'phags pa rdo rje ri rab chen po'i rtse mo'i khang pa brtsegs pa'i gzungs</tib>
<skttrans></skttrans>
<coloph>'phags pa rdo rje ri rab chen po'i rtse mo'i khang pa brtsegs pa'i gzungs / rdzogs so // // rgya gar gyi mkhan po shi len dra bo dhi dang / dznya na sid dhi dang / zhu chen gyi la tstsha ba ban dhe ye shes sdes bsgyur cing zhus te skad gsar chad kyis kyang bcos nas gtan la phab pa</coloph>
<note></note>
</item>

<item>
<rkts>751</rkts>
<ref>W50.02</ref>
<loc>Pander Pantheon 50 (1111). / Wanli Kanjur, rgyud, vol. YA, fol.33b7-45b3</loc>
<tib>'phags pa stobs po che zhes bya ba theg pa chen po'i mdo</tib>
<skttrans></skttrans>
<coloph>'phags pa stobs po che zhes bya ba theg pa chen po'i mdo rdzogs s.ho</coloph>
<note></note>
</item>

<item>
<rkts>742</rkts>
<ref>W50.03</ref>
<loc>Pander Pantheon 50 (1111). / Wanli Kanjur, rgyud, vol. YA, fol.45b5-46b7</loc>
<tib>'phags pa lag na rdo rje gos sngon po can gyi cho ga zhes bya ba'i gzungs</tib>
<skttrans></skttrans>
<coloph>'phags pa lag na rdo rje gos sngon po can gyi cho ga zhes bya ba'i gzungs / rdzogs s.ho // // rgya gar gyi mkhan po di paM ka ra shri dznya na dang / bod gyi lo tstsha ba rgya brtson 'grus seng ges dpal na len dra'i sgo 'gram du bsgyur</coloph>
<note></note>
</item>

<item>
<rkts>744</rkts>
<ref>W50.04</ref>
<loc>Pander Pantheon 50 (1111). / Wanli Kanjur, rgyud, vol. YA, fol.46b7-48a6</loc>
<tib>rdo rje rnam par 'joms pa zhes bya ba'i kzungs</tib>
<skttrans></skttrans>
<coloph>rdo rje rnam par 'joms pa zhes bya ba'i gzungs / rdzogs sto // // rgya gar gyi mkhan po dzi na mi tra dang / da na shI la dang / bod gyi lo tstsha ba ban dha ye shes sdes bsgyur cing zhus te gtan la phab ba</coloph>
<note></note>
</item>

<item>
<rkts>743</rkts>
<ref>W50.05</ref>
<loc>Pander Pantheon 50 (1111). / Wanli Kanjur, rgyud, vol. YA, fol.48a6-49b4</loc>
<tib>'phags pa lag na rdo rje'i mtshan brgyad po gsang sngags dang bcas pa</tib>
<skttrans></skttrans>
<coloph>lag na rdo rje'i mtshan brgyad po gsang sngags dang bcas pa / rdzogs s.ho</coloph>
<note></note>
</item>

<item>
<rkts>748</rkts>
<ref>W50.06</ref>
<loc>Pander Pantheon 50 (1111). / Wanli Kanjur, rgyud, vol. YA, fol.49b4-50b4</loc>
<tib>'phaks pa lag na rdo rje bcu'i snying po</tib>
<skttrans></skttrans>
<coloph>'phags pa lag na rdo rje bcu'i snying po rdzogs s.ho // // rgya gar gyi mkhan po dzi na mi tra dang / da na shI la dang / zhu chen gyi lo tstsha ba ban dhe ye shes sdes bsgyur cing zhus te gtan la pha pa</coloph>
<note></note>
</item>

<item>
<rkts>946</rkts>
<ref>W50.07</ref>
<loc>Pander Pantheon 50 (1111). / Wanli Kanjur, rgyud, vol. YA, fol.50b4-50b5</loc>
<tib>rmi lam mthong ba zhes bya ba'i gzungs</tib>
<skttrans></skttrans>
<coloph>rmi lam mthong ba zhes bya ba'i gzungs I rdzogs s.ho</coloph>
<note></note>
</item>

<item>
<rkts>953</rkts>
<ref>W50.08</ref>
<loc>Pander Pantheon 50 (1111). / Wanli Kanjur, rgyud, vol. YA, fol.50b5-51b6</loc>
<tib>phyag na rdo rje gnod sbyin gyi bdag po'i gzungs</tib>
<skttrans></skttrans>
<coloph>phyag na rdo rje gnod sbyin gyi bdag po'i gzungs I rdzogs so</coloph>
<note></note>
</item>

<item>
<rkts>746</rkts>
<ref>W50.09</ref>
<loc>Pander Pantheon 50 (1111). / Wanli Kanjur, rgyud, vol. YA, fol.51b6-55a5</loc>
<tib>'phags pa rdo rje mi 'pham pa me lta rab tu rmongs bycd ces bya ba'i gzungs</tib>
<skttrans></skttrans>
<coloph>'phags pa rdo rje mi 'pham pa me ltar rab tu rmongs byed ces bya ba' gzungs / rdzogs s.ho // // rgya gar gyi mkhan po dzi na mi tra dang / da na shI la dang / zhu chen gyi lo tstsha ba ban dhe ye shes sdes bsgyur cing zhus te skad gsar chad kyis kyang bcos nas gtan la phab pa</coloph>
<note></note>
</item>

<item>
<rkts>747</rkts>
<ref>W50.10</ref>
<loc>Pander Pantheon 50 (1111). / Wanli Kanjur, rgyud, vol. YA, fol.55a5-55b8</loc>
<tib>rdo rje phra mo thogs pa med pa zhes bya ba'i gzungs</tib>
<skttrans></skttrans>
<coloph>rdo rje phra mo thogs pa med pa zhes bya ba'i gzungs / rdzogs sto</coloph>
<note></note>
</item>

<item>
<rkts>599</rkts>
<ref>W50.11</ref>
<loc>Pander Pantheon 50 (1111). / Wanli Kanjur, rgyud, vol. YA, fol.55b8-56a2</loc>
<tib>'phags pa rdo rje 'jigs byed kyi gzungs zhes bya ba</tib>
<skttrans></skttrans>
<coloph>'phags pa rdo rje 'jigs byed kyi gzungs zhes bya ba/ ma rungs ba phyir bzlog pa / rdzogs so // 'phags pas gsungs pa'i gzungs rnams rnam mang yang / rdo rje 'jigs byed zhal nas gsungs pa'i gzungs / / bsrung bya'i las bdun ldan ba'i gzungs mchog 'di / / kun gyi thun mong ma yin rnal 'byor dam pa'i gzungs / / rnal 'byor gyi rnal 'byor chen po don yod rdo rje'i zhal snga nas bsgyur nas / bod kyi ban dhe skye 'od 'byung la gnang ngo</coloph>
<note></note>
</item>

<item>
<rkts>749</rkts>
<ref>W50.12</ref>
<loc>Pander Pantheon 50 (1111). / Wanli Kanjur, rgyud, vol. YA, fol.56a2-58b4</loc>
<tib>'phags pa bdud rtsi thab sbyor gyi snying po bzhi pa zhes bya ba'i gzungs</tib>
<skttrans></skttrans>
<coloph>'phags pa bdud rtsi thab sbyor gyi snying po / rdzogs s.ho</coloph>
<note></note>
</item>

<item>
<rkts>600</rkts>
<ref>W50.13</ref>
<loc>Pander Pantheon 50 (1111). / Wanli Kanjur, rgyud, vol. YA, fol.58b4-61a1</loc>
<tib>'phags pa be con chen po zhes bya pa'i gzungs</tib>
<skttrans></skttrans>
<coloph>'phags pa be con chen po zhes bya ba theg pa chen po'i mdo / rdzogs s.ho // // rgya gar gyi mkhan po 'dzi na mi tra dang / da na shi la dang / zhu chen gyi lo tstsha ba ban dhe ye shes sdes bsgyur cing zhus te / skad gsar chad kyis kyang bcos nas gtan la phab ba</coloph>
<note></note>
</item>

<item>
<rkts>649</rkts>
<ref>W50.14</ref>
<loc>Pander Pantheon 50 (1111). / Wanli Kanjur, rgyud, vol. YA, fol.61a1-61a8</loc>
<tib>'phags pa bgegs sel ba'i gzungs</tib>
<skttrans></skttrans>
<coloph>'phags pa bgegs sel ba zhes bya ba'i gzungs rdzogs s.ho // gu gul ser po dang / pha pad gi rtug pa kun la rku ba'i rtug pa sbyar pa'i du bas bdugs na / 'go ba'i nad pa'i gan du phyin yang mi tshugs / gos pa la thug na nyur du sel / khyim du 'byung po gnod pa dag la rab tu bsngags so</coloph>
<note></note>
</item>

<item>
<rkts>731</rkts>
<ref>W50.15</ref>
<loc>Pander Pantheon 50 (1111). / Wanli Kanjur, rgyud, vol. YA, fol.61a8-62a1</loc>
<tib>'phags pa phyir zlog pa stobs can zhes bya'o</tib>
<skttrans></skttrans>
<coloph>'phags pa phyir zlog pa stobs can zhes bya ba'i gzungs / rdzogs s.ho</coloph>
<note></note>
</item>

<item>
<rkts>623</rkts>
<ref>W50.16</ref>
<loc>Pander Pantheon 50 (1111). / Wanli Kanjur, rgyud, vol. YA, fol.62a1-62b3</loc>
<tib>'phags pa mi rgod rnam par 'joms pa zhes bya ba'i gzungs</tib>
<skttrans></skttrans>
<coloph>'phags pa mi rgod rnam par 'joms pa zhes bya ba'i gzungs rdzogs.hyo</coloph>
<note></note>
</item>

<item>
<rkts>594</rkts>
<ref>W50.17</ref>
<loc>Pander Pantheon 50 (1111). / Wanli Kanjur, rgyud, vol. YA, fol.62b3-62b5</loc>
<tib>gtsug tor 'bar ba zhes bya ba'i gzungs</tib>
<skttrans></skttrans>
<coloph>gtsug tor 'bar ba zhes bya ba'i gzungs rdzogs.hyo</coloph>
<note></note>
</item>

<item>
<rkts>625</rkts>
<ref>W50.18</ref>
<loc>Pander Pantheon 50 (1111). / Wanli Kanjur, rgyud, vol. YA, fol.62b5-63b4</loc>
<tib>'phags pa khro bo mi gyo ba'i gzungs zhes bya ba</tib>
<skttrans></skttrans>
<coloph>'phags pa khro bo mi gyo ba zhes bya ba'i gzungs rdzogs.hyo // // pan ti ta dharma ta shi dang / latstsha ba dge slong chos kyi bzang pos bsgyur ba'o</coloph>
<note></note>
</item>

<item>
<rkts>753</rkts>
<ref>W50.19</ref>
<loc>Pander Pantheon 50 (1111). / Wanli Kanjur, rgyud, vol. YA, fol.63b4-86a8</loc>
<tib>rdo rje mchu zhes bya ba klu'i dam tshig go</tib>
<skttrans></skttrans>
<coloph>rdo rje mchu'i cho ga rdzogs s.hyo</coloph>
<note></note>
</item>

<item>
<rkts>754</rkts>
<ref>W50.20</ref>
<loc>Pander Pantheon 50 (1111). / Wanli Kanjur, rgyud, vol. YA, fol.86a8-88a5</loc>
<tib>rdo rje gnam lcags mchu zhes bya ba'i gzungs</tib>
<skttrans></skttrans>
<coloph>rdo rje gnam lcags mchu zhes bya ba'i gzungs / rdzogs.ho</coloph>
<note></note>
</item>

<item>
<rkts>757</rkts>
<ref>W50.21</ref>
<loc>Pander Pantheon 50 (1111). / Wanli Kanjur, rgyud, vol. YA, fol.88a5-90a2</loc>
<tib>'phags pa lcags mchu nag po</tib>
<skttrans></skttrans>
<coloph>'phags pa lcags mchu nag po'i gzungs rdzogs s.hyo</coloph>
<note></note>
</item>

<item>
<rkts>612</rkts>
<ref>W50.22</ref>
<loc>Pander Pantheon 50 (1111). / Wanli Kanjur, rgyud, vol. YA, fol.90a2-90b5</loc>
<tib>'phags pa mdangs phyir 'phrog pa zhas bya ba'i mdo</tib>
<skttrans></skttrans>
<coloph>'phags pa mdangs phyir 'phrog pa zhes bya ba theg pa chen po'i mdo rdzogs.ho</coloph>
<note></note>
</item>

<item>
<rkts>728</rkts>
<ref>W50.23</ref>
<loc>Pander Pantheon 50 (1111). / Wanli Kanjur, rgyud, vol. YA, fol.90b5-92a4</loc>
<tib>phyir zlog pa 'phags pa rnam par rgyal ba can zhes bya ba'o</tib>
<skttrans></skttrans>
<coloph>phyir zlog pa 'phags pa rnam par rgyal ba can zhes bya ba / rdzogs.ho</coloph>
<note></note>
</item>

<item>
<rkts>767</rkts>
<ref>W50.24</ref>
<loc>Pander Pantheon 50 (1111). / Wanli Kanjur, rgyud, vol. YA, fol.92a4-92b6</loc>
<tib>'phags pa rig sngags kyi rgyal po dbags chen po zhes bya ba</tib>
<skttrans></skttrans>
<coloph>'phags pa rig sngags kyi rgyal po dbugs chen po zhes bya ba rdzogs.ho // rgya gar gyi mkhan po pradznya bar ma dang / zhu chen gyi lo tstsha ba san de ye shes sdes bsgyur cing zhus te gtan la phab pa</coloph>
<note></note>
</item>

<item>
<rkts>758</rkts>
<ref>W50.25</ref>
<loc>Pander Pantheon 50 (1111). / Wanli Kanjur, rgyud, vol. YA, fol.92b6-93a8</loc>
<tib>'phags pa nor bu bzang po'i gzungs shes bya ba</tib>
<skttrans></skttrans>
<coloph>'phags pa nor bu bzang po'i gzungs shes bya ba rdzogs.hyo // // rgya gar gyi mkhan po bid dya ka ra sing ha dang / lo tstsha ba ban de klu'i dbang pos bsgyur</coloph>
<note></note>
</item>

<item>
<rkts>763</rkts>
<ref>W50.26</ref>
<loc>Pander Pantheon 50 (1111). / Wanli Kanjur, rgyud, vol. YA, fol.93a8-93b8</loc>
<tib>'phags pa gnod 'dzin chu dbang snying rje can gyi gzungs bde byed ces bya ba</tib>
<skttrans></skttrans>
<coloph>'phags pa gnod 'dzin chu dbang snying rje can gyi gzungs bde byed ces bya ba rdzogs s.hyo</coloph>
<note></note>
</item>

<item>
<rkts>765</rkts>
<ref>W50.27</ref>
<loc>Pander Pantheon 50 (1111). / Wanli Kanjur, rgyud, vol. YA, fol.93b8-95b4</loc>
<tib>'phags pa gnod 'dzin gyi mtshan brgya rtsa brgyad pa</tib>
<skttrans></skttrans>
<coloph>'phags pa gnod 'dzin gyi mtshan brgya rtsa brgyad pa / rdzogs.hyo</coloph>
<note></note>
</item>

<item>
<rkts>762</rkts>
<ref>W50.28</ref>
<loc>Pander Pantheon 50 (1111). / Wanli Kanjur, rgyud, vol. YA, fol.95b4-96b3</loc>
<tib>'phags pa gnod 'dzin dpal zhes bya ba'i gzungs</tib>
<skttrans></skttrans>
<coloph>'phags pa gnod 'dzin dpal zhes bya ba'i gzungs rdzogs.ho</coloph>
<note></note>
</item>

<item>
<rkts>313</rkts>
<ref>W50.29</ref>
<loc>Pander Pantheon 50 (1111). / Wanli Kanjur, rgyud, vol. YA, fol.96b3-98b8</loc>
<tib>'pags pa mtshan mo bzang po zhes bya ba'i mdo</tib>
<skttrans></skttrans>
<coloph>'phags pa mchan mo bzang po zhes bya ba'i mdo rdzogs.ho // // rgya gar gyi mkhan po dzi na mi tra dang / da na shI la dang / zhu chen gyi lo tstsha ba ban dhe ye shes sdes bsgyur cing zhus te / skad gsar chad kyis kyang bcos gtan la phab pa</coloph>
<note></note>
</item>

<item>
<rkts>648</rkts>
<ref>W50.30</ref>
<loc>Pander Pantheon 50 (1111). / Wanli Kanjur, rgyud, vol. YA, fol.98b8-102a2</loc>
<tib>'phags pa chos kyi rgya mcho zhes bya ba'i gzungs</tib>
<skttrans></skttrans>
<coloph>'phags pa chos kyi rgya mtsho zhes bya ba'i gzungs rdzogs.hyo // / rgya gar gyi mkhan po su ren dra bo dhi dang / pradznya bar ma dang / zhu chen gyi lo tstsha ba ban dhe ye shes sde la sogs pas bsgyur cing zhus te gtan la phab pa</coloph>
<note></note>
</item>

<item>
<rkts>609</rkts>
<ref>W50.31</ref>
<loc>Pander Pantheon 50 (1111). / Wanli Kanjur, rgyud, vol. YA, fol.102a2-102b3</loc>
<tib>'phags pa bu mang po ston pa zhes bya ba'i gzungs</tib>
<skttrans></skttrans>
<coloph>'phags pa bu mang po ston pa zhes bya ba'i gzungs rdzogs.hyo // // rgya gar gyi mkhan po 'dzi na mi tra dang / dA na shI la dang / zhu chen gyi lo tstsha ba ban dhe ye shes sdes bsgyur cing zhus te gtan la phab pa</coloph>
<note></note>
</item>

<item>
<rkts>523</rkts>
<ref>W50.32</ref>
<loc>Pander Pantheon 50 (1111). / Wanli Kanjur, rgyud, vol. YA, fol.102b3-103a1</loc>
<tib>'phags pa gdon mi za ba zhes bya ba'i gzungs</tib>
<skttrans></skttrans>
<coloph>'phags pa gdon mi za ba zhes bya ba'i gzungs rdzogs.ho</coloph>
<note></note>
</item>

<item>
<rkts>703</rkts>
<ref>W50.33</ref>
<loc>Pander Pantheon 50 (1111). / Wanli Kanjur, rgyud, vol. YA, fol.103a1-103a4</loc>
<tib>gzhan gyis mi thub pa'i rig pa chen po</tib>
<skttrans></skttrans>
<coloph>gzhan gyis mi thub pa'i rig pa chen po rdzogs.ho</coloph>
<note></note>
</item>

<item>
<rkts>518</rkts>
<ref>W50.34</ref>
<loc>Pander Pantheon 50 (1111). / Wanli Kanjur, rgyud, vol. YA, fol.103a4-105b2</loc>
<tib>'phags pa rten cing 'brel bar 'byung ba'i snying bo'i cho ga'i gzungs</tib>
<skttrans></skttrans>
<coloph>'phags pa rten cing 'brel bar 'byung ba'i snying po'i cho ga'i gzungs / rdzogs.ho</coloph>
<note></note>
</item>

<item>
<rkts>212</rkts>
<ref>W50.35</ref>
<loc>Pander Pantheon 50 (1111). / Wanli Kanjur, rgyud, vol. YA, fol.105b2-106a8</loc>
<tib>'phags pa rten cing 'brel bar 'byung ba zhes bya ba theg pa chen po 'i mdo</tib>
<skttrans></skttrans>
<coloph>'phags pa rten cing 'brel bar 'byung ba zhes bya ba theg pa chen po 'i mdo / rdzogs.hyo</coloph>
<note></note>
</item>

<item>
<rkts>520</rkts>
<ref>W50.36</ref>
<loc>Pander Pantheon 50 (1111). / Wanli Kanjur, rgyud, vol. YA, fol.106a8-106b3</loc>
<tib>rten cing 'brel bar 'byung ba'i snying po</tib>
<skttrans></skttrans>
<coloph>rten cing 'brel bar 'byung ba'i snying po / rdzogs.ho</coloph>
<note></note>
</item>

<item>
<rkts>509</rkts>
<ref>W50.37</ref>
<loc>Pander Pantheon 50 (1111). / Wanli Kanjur, rgyud, vol. YA, fol.106b3-117b4</loc>
<tib>'phags pa 'od zer dri ma med pa rnam par dag pa'i 'od ces bya ba'i gzung lags</tib>
<skttrans></skttrans>
<coloph>'phags pa 'od zer dri ma mad pa rnam par dag pa'i 'od ces bya ba'i gzungs rdzogs s.ho // // rgya gar gyi mkhan po bidya ka ra si ha dang / zhu chen gyi lo tstsha ba ban de dpal gyi lhun po'i sdes bsgyur cing zhus te gtan la phab pa'o // jo bo a dhi sha dang dge bshes 'brom ston pas sngags rnams dag par bsgyur ba'o</coloph>
<note></note>
</item>

<item>
<rkts>593</rkts>
<ref>W50.38</ref>
<loc>Pander Pantheon 50 (1111). / Wanli Kanjur, rgyud, vol. YA, fol.117b4-127b4</loc>
<tib>kun nas sgor 'jug ba'i 'od zer gtsug tor dri ma med par snang ba de bzhin gshegs pa thams cad kyi snying po dang dam tshig la rnam par lta pa zhes bya ba'i gzungs</tib>
<skttrans></skttrans>
<coloph>'phags pa kun nas sgor 'jug ba'i 'od zer gtsug tor dri ma med par snang ba de bzhin gshegs pa thams cad kyi snying po dang dam tshig la rnam par lta pa zhes bya ba'i gzungs / rdzogs s.ho // // rgya gar gyi mkhan po dzi na mi tra dang / shI len dra bo dhi dang / zhu chen gyi lo tstsha ba ban de ye shes sdes bsgyur cing zhus te btan la phab pa</coloph>
<note></note>
</item>

<item>
<rkts>591</rkts>
<ref>W50.39</ref>
<loc>Pander Pantheon 50 (1111). / Wanli Kanjur, rgyud, vol. YA, fol.127b4-132b7</loc>
<tib>'phags pa ngan 'gro thams cad yongs su spyod ba gtsug tor rnam par rgyal ba zhes bya ba'i gzungs</tib>
<skttrans></skttrans>
<coloph>'phags pa ngan 'gro thams cad yongs su spyod ba / gtsug tor rnam par rgyal ba zhes bya ba'i gzungs / rdzogs s.ho // // rgya gar gyi mkhan po dzi na mi tra dang / su ren dra bo dhi dang / zhu chen gyi lo tstsha ba ban dhe ye shes sdes bsgyur cing zhus te gtan la phab ba</coloph>
<note></note>
</item>

<item>
<rkts>584</rkts>
<ref>W50.40</ref>
<loc>Pander Pantheon 50 (1111). / Wanli Kanjur, rgyud, vol. YA, fol.132b7-141a3</loc>
<tib>'phags pa de bzhin gshegs pa thams cad kyi gtsug tor nas byung ba'i gdugs dkar po nan zhes bya ba gzhan gyis mi thub phyir zlog pa'i rig sngags kyi rgyal mo chen mo</tib>
<skttrans></skttrans>
<coloph>'phags pa de bzhin gshegs pa thams cad kyi gcug tor nas byung ba gdugs dkar po can zhes bya ba gzhan gyis mi thub ma phyir zlog pa rig sngags kyi rgyal mo chen mo / rdzogs s.ho</coloph>
<note></note>
</item>

<item>
<rkts>586</rkts>
<ref>W50.41</ref>
<loc>Pander Pantheon 50 (1111). / Wanli Kanjur, rgyud, vol. YA, fol.141a3-146a1</loc>
<tib>'phags pa de bzhin gshegs pa'i gcug tor nas byung ba'i gdugs dkar mo can gzhan gyis mi thub ma zhes bya ba'i gzungs</tib>
<skttrans></skttrans>
<coloph>'phags pa de bzhin gshegs pa'i gtsug tor nas byung ba'i gdugs dkar po can gzhan gyis mi thub ma zhes bya ba'i gzungs / rdzogs s.ho</coloph>
<note></note>
</item>

<item>
<rkts>987</rkts>
<ref>W50.42</ref>
<loc>Pander Pantheon 50 (1111). / Wanli Kanjur, rgyud, vol. YA, fol.146a1-149a4</loc>
<tib>dpal lha mo gtsug tor rol ba'i tan tra</tib>
<skttrans></skttrans>
<coloph>dpal lha mo gtsug tor rol ba'i tan tra / rdzogs s.ho</coloph>
<note></note>
</item>

<item>
<rkts>559</rkts>
<ref>W50.43</ref>
<loc>Pander Pantheon 50 (1111). / Wanli Kanjur, rgyud, vol. YA, fol.149a4-150a5</loc>
<tib>'phags rna 'od zer can zhes bya ba'i gzungs</tib>
<skttrans></skttrans>
<coloph>'phags pa 'od zer can zhes bya ba'i gzungs / rdzogs s.ho // // pan di ta a mo gha badzra dang / lotstsha ba dge slong ba ri rin chen grags pas bsgyur ba'o</coloph>
<note></note>
</item>

<item>
<rkts>607</rkts>
<ref>W50.44</ref>
<loc>Pander Pantheon 50 (1111). / Wanli Kanjur, rgyud, vol. YA, fol.150a5-151a1</loc>
<tib>'phags pa lha mo skul byed ma zhes bya ba'i gzungs</tib>
<skttrans></skttrans>
<coloph>'phags pa lha ma skul byed ma zhes bya ba'i gzungs / rdzogs s.ho</coloph>
<note></note>
</item>

<item>
<rkts>566</rkts>
<ref>W50.45</ref>
<loc>Pander Pantheon 50 (1111). / Wanli Kanjur, rgyud, vol. YA, fol.151a1-151b6</loc>
<tib>'phags pa dug sel ces bya ba'i rig sngags</tib>
<skttrans></skttrans>
<coloph>'phags pa dug sel ces bya ba'i rig sngags // rdzogs s.ho</coloph>
<note></note>
</item>

<item>
<rkts>565</rkts>
<ref>W50.46</ref>
<loc>Pander Pantheon 50 (1111). / Wanli Kanjur, rgyud, vol. YA, fol.151b6-153b3</loc>
<tib>'phags pa dbyig dang ldan pa zhes bya ba'i gzungs</tib>
<skttrans></skttrans>
<coloph>'phags pa dbyig dang ldan pa zhes bya ba'i gzungs / rdzogs s.ho // // rgya gar gyi mkhan po 'dzi na mi tra dang / da na shI la dang / zhu chen gyi lo tshtsha ba ban de ye shes sdes bsgyur cing zhus te skad gsad gsar chad kyis kyang bcos nas gtan la phab pa</coloph>
<note></note>
</item>

<item>
<rkts>726</rkts>
<ref>W50.47</ref>
<loc>Pander Pantheon 50 (1111). / Wanli Kanjur, rgyud, vol. YA, fol.153b3-154a5</loc>
<tib>'phags pa grags ldan ma'i gzungs</tib>
<skttrans></skttrans>
<coloph>'phags pa grags ldan ma'i gzungs / rdzogs s.ho</coloph>
<note></note>
</item>

<item>
<rkts>567</rkts>
<ref>W50.48</ref>
<loc>Pander Pantheon 50 (1111). / Wanli Kanjur, rgyud, vol. YA, fol.154a4-155a3</loc>
<tib>klags pas grub pa bcom ldan 'das ma 'phags ma sor mo can zhes bya ba rig ba'i rgyal mo</tib>
<skttrans></skttrans>
<coloph>klags pas 'grub pa bcom ldan 'das ma 'phags ma sor mo can zhes bya ba rig ba'i rgyal mo chen mo / rdzogs s.ho</coloph>
<note></note>
</item>

<item>
<rkts>729</rkts>
<ref>W50.49</ref>
<loc>Pander Pantheon 50 (1111). / Wanli Kanjur, rgyud, vol. YA, fol.155a3-156a5</loc>
<tib>'phags pa parnna sha ni'i mdo</tib>
<skttrans></skttrans>
<coloph>'phags pa panna sha ba ri'i mdo / rdzogs s.ho</coloph>
<note></note>
</item>

<item>
<rkts>730</rkts>
<ref>W50.50</ref>
<loc>Pander Pantheon 50 (1111). / Wanli Kanjur, rgyud, vol. YA, fol.156a6-156b6</loc>
<tib>'phags pa ri khrod lo ma gyon ba'i gzungs</tib>
<skttrans></skttrans>
<coloph>'phags pa ri khrod le ma gyon ba'i gzungs</coloph>
<note></note>
</item>

<item>
<rkts>568</rkts>
<ref>W50.51</ref>
<loc>Pander Pantheon 50 (1111). / Wanli Kanjur, rgyud, vol. YA, fol.156b6-157a4</loc>
<tib>chos thams cad kyi yum zhes bya ba'i gzungs</tib>
<skttrans></skttrans>
<coloph>chos thams cad kyi yum zhes bya ba rdzogs s.ho</coloph>
<note></note>
</item>

<item>
<rkts>654</rkts>
<ref>W50.52</ref>
<loc>Pander Pantheon 50 (1111). / Wanli Kanjur, rgyud, vol. YA, fol.157a4-160a8</loc>
<tib>'phags ma gza' rnams kyi yum zhes bya ba'i gzungs</tib>
<skttrans></skttrans>
<coloph>'phags ma gza' rnams kyi yum zhes bya ba'i gzungs / rdzogs s.ho // // gyal blon byang chub sems dpa' rnams kyi sku ring la bsgyur ba las dus phyis dge bsnyen grags pa rgyal mtshan gyis dpal ldan sa skya'i dben gnas su rgya dpe la gtugs nas shin tu dag par byas pa'o</coloph>
<note></note>
</item>

<item>
<rkts>655</rkts>
<ref>W50.53</ref>
<loc>Pander Pantheon 50 (1111). / Wanli Kanjur, rgyud, vol. YA, fol.160a8-163a2</loc>
<tib>gza' rnams kyi yum zhes bya ba'i gzungs</tib>
<skttrans></skttrans>
<coloph>gza' rnams kyi yum zhes bya ba'i gzungs / rdzogs so</coloph>
<note></note>
</item>

<item>
<rkts>496</rkts>
<ref>W50.54</ref>
<loc>Pander Pantheon 50 (1111). / Wanli Kanjur, rgyud, vol. YA, fol.163a2-164b1</loc>
<tib>'phags pa lha mo brgyad kyi gzungs</tib>
<skttrans></skttrans>
<coloph>'phags pa lha mo brgyad kyi gzungs / rdzogs so // // rgya gar gyi mkhan po shI len dra bo dhi dang / zhu chen gyi lo tstsha ba ban de ye shes sdes bsgyur cing zhus ta gtan la phab pa</coloph>
<note></note>
</item>

<item>
<rkts>721</rkts>
<ref>W50.55</ref>
<loc>Pander Pantheon 50 (1111). / Wanli Kanjur, rgyud, vol. YA, fol.164b1-166b5</loc>
<tib>rje btsun 'phags rna sgrol ma'i mchan brgya rtsa brgyad pa</tib>
<skttrans></skttrans>
<coloph>Ije bcun 'phags ma sgrol ma'i mchan brgya rtsa brgyad pa / rdzogs s.ho</coloph>
<note></note>
</item>

<item>
<rkts>723</rkts>
<ref>W50.56</ref>
<loc>Pander Pantheon 50 (1111). / Wanli Kanjur, rgyud, vol. YA, fol.166b5-166b6</loc>
<tib>'phags ma sgrol ma'i gzungs</tib>
<skttrans></skttrans>
<coloph>'phags ma sgrol ma'i gzungs / rdzogs s.ho</coloph>
<note></note>
</item>

<item>
<rkts>724</rkts>
<ref>W50.57</ref>
<loc>Pander Pantheon 50 (1111). / Wanli Kanjur, rgyud, vol. YA, fol.166b6-167a4</loc>
<tib>'phags ma sgrol ma rang gis dam bcas pa zhes bya ba'i gzungs</tib>
<skttrans></skttrans>
<coloph>'phags ma sgrol ma rang gis dam bcas pa'i gzungs / rdzogs so</coloph>
<note></note>
</item>

<item>
<rkts>562</rkts>
<ref>W50.58</ref>
<loc>Pander Pantheon 50 (1111). / Wanli Kanjur, rgyud, vol. YA, fol.167a4-173a7</loc>
<tib>'phags ma rig sngags kyi rgyal mo chen mo rgyal ba can zhes bya ba</tib>
<skttrans></skttrans>
<coloph>'phags pa rig sngags kyi rgyal mo chen mo rgyal ba can zhes bya ba // rdzogs s.ho // / rgya gar gyi mkhan po 'dzi na mi tra dang / pan shI la dang / zhu chen gyi lo tstsha ba ban dhe ye shes sdes bsgyur cing zhus te gtan la phab pa</coloph>
<note></note>
</item>

<item>
<rkts>563</rkts>
<ref>W50.59</ref>
<loc>Pander Pantheon 50 (1111). / Wanli Kanjur, rgyud, vol. YA, fol.173a7-177b1</loc>
<tib>'phags pa rgyal ba can zhes bya ba'i gzungs</tib>
<skttrans></skttrans>
<coloph>'phags pa rgyal ba can zhes bya ba'i gzungs / rdzogs s.ho</coloph>
<note></note>
</item>

<item>
<rkts>734</rkts>
<ref>W50.60</ref>
<loc>Pander Pantheon 50 (1111). / Wanli Kanjur, rgyud, vol. YA, fol.177b1-178a4</loc>
<tib>'phags pa dpal chen mo'i mdo</tib>
<skttrans></skttrans>
<coloph>'phags pa dpal chen mo'i mdo / rdzogs s.ho // // rgya gar gyi mkhan po 'dzi na mi tra dang / zhu chen gyi lo tstsha ba man dhe ye shes sdes bsgyur cing zhus te gtan la phab pa</coloph>
<note></note>
</item>

<item>
<rkts>735</rkts>
<ref>W50.61</ref>
<loc>Pander Pantheon 50 (1111). / Wanli Kanjur, rgyud, vol. YA, fol.178a4-178b6</loc>
<tib>dpal gyi lha mo'i mtshan bcu gnyis pa</tib>
<skttrans></skttrans>
<coloph>dpal gyi lha mo chen mo'i mtshan bcu gnyis pa rdzogs s.ho</coloph>
<note></note>
</item>

<item>
<rkts>656</rkts>
<ref>W50.62</ref>
<loc>Pander Pantheon 50 (1111). / Wanli Kanjur, rgyud, vol. YA, fol.178b6-182b8</loc>
<tib>'phags pa nor gyi rgyun ces bya ba'i gzungs</tib>
<skttrans></skttrans>
<coloph>'phags pa nor gyi rgyun ces bya ba'i gzungs rdzogs s.ho</coloph>
<note></note>
</item>

<item>
<rkts>613</rkts>
<ref>W50.63</ref>
<loc>Pander Pantheon 50 (1111). / Wanli Kanjur, rgyud, vol. YA, fol.182b8-184a8</loc>
<tib>'phags pa mig rnam par sdod pa zhes bya ba'i rig sngags</tib>
<skttrans></skttrans>
<coloph>'phags pa mig rnam par sbyong ba zhes bya pa'i rig sngags rdzogs s.ho</coloph>
<note></note>
</item>

<item>
<rkts>737</rkts>
<ref>W50.64</ref>
<loc>Pander Pantheon 50 (1111). / Wanli Kanjur, rgyud, vol. YA, fol.184a8-185b1</loc>
<tib>'phags pa las kyi sgrib pa thams rnam par sbyong ba zhes bya ba'i gzungs</tib>
<skttrans></skttrans>
<coloph>'phags pa las kyi sgrib pa thams cad rnam par sbyong ba'i gzungs rdzogs s.ho</coloph>
<note></note>
</item>

<item>
<rkts>624</rkts>
<ref>W50.65</ref>
<loc>Pander Pantheon 50 (1111). / Wanli Kanjur, rgyud, vol. YA, fol.185b1-185b8</loc>
<tib>'phags ba bar du gcod pa thams cad sel ba'i gzungs sngags</tib>
<skttrans></skttrans>
<coloph>'phags pa bar du gcod pa thams cad sel ba'i gzungs sngags rdzogs s.ho</coloph>
<note></note>
</item>

<item>
<rkts>771</rkts>
<ref>W50.66</ref>
<loc>Pander Pantheon 50 (1111). / Wanli Kanjur, rgyud, vol. YA, fol.185a8-186a5</loc>
<tib>yon yongs su sbyong ba zhes bya ba</tib>
<skttrans></skttrans>
<coloph>'dul ba lung las rnam par nges pa'i mdo las byung ba yon yongs su sbyong ba rdzogs s.ho</coloph>
<note></note>
</item>

<item>
<rkts>772</rkts>
<ref>W50.67</ref>
<loc>Pander Pantheon 50 (1111). / Wanli Kanjur, rgyud, vol. YA, fol.186a5-186a7</loc>
<tib>yon yongs su sbyong ba'i gzungs</tib>
<skttrans></skttrans>
<coloph>yon yongs su sbyong ba'i gzungs rdzogs s.ho</coloph>
<note></note>
</item>

<item>
<rkts>776</rkts>
<ref>W50.68</ref>
<loc>Pander Pantheon 50 (1111). / Wanli Kanjur, rgyud, vol. YA, fol.186a7-186b3</loc>
<tib>ngan song thams cad yengs su sbyong ba zhes bya ba'i gzungs</tib>
<skttrans></skttrans>
<coloph>ngan song thams cad yengs su sbyong ba zhes bya ba'i gzungs rdzogs s.ho</coloph>
<note></note>
</item>

<item>
<rkts>616</rkts>
<ref>W50.69</ref>
<loc>Pander Pantheon 50 (1111). / Wanli Kanjur, rgyud, vol. YA, fol.186b3-187a3</loc>
<tib>'phags pa nad thams cad rab tu zhi bar byed ba'i gzungs</tib>
<skttrans></skttrans>
<coloph>'phags pa nad thams cad rab tu zhi bar byed ba'i gzungs rdzogs s.ho</coloph>
<note></note>
</item>

<item>
<rkts>619</rkts>
<ref>W50.70</ref>
<loc>Pander Pantheon 50 (1111). / Wanli Kanjur, rgyud, vol. YA, fol.187a3-187b6</loc>
<tib>'phags pa rims nad rab tu zhi bar bye pa zhes bya ba'i gzungs</tib>
<skttrans></skttrans>
<coloph>'phags pa rims nad rab tu zhi bar bye pa zhes bya ba'i gzungs rdzogs s.ho // // rgya gar gyi mkhan po 'dzin mi tra dang / da na shi la dang / zhu chen gyi lo tstsha ba ban dhe ye shes sdes bsgyur cing zhus te gtan la phab pa</coloph>
<note></note>
</item>

<item>
<rkts>618</rkts>
<ref>W50.71</ref>
<loc>Pander Pantheon 50 (1111). / Wanli Kanjur, rgyud, vol. YA, fol.187b6-187b7</loc>
<tib>rims nad zhi ba'i gzungs</tib>
<skttrans></skttrans>
<coloph>rims nad zhi ba'i gzungs rdzogs s.ho</coloph>
<note></note>
</item>

<item>
<rkts>614</rkts>
<ref>W50.72</ref>
<loc>Pander Pantheon 50 (1111). / Wanli Kanjur, rgyud, vol. YA, fol.187b7-188a5</loc>
<tib>'phags pa mig nad rab tu zhi bar byed pa'i mdo</tib>
<skttrans></skttrans>
<coloph>'phags pa mig nad rab tu zhi bar byed pa'i mdo rdzogs s.ho</coloph>
<note></note>
</item>

<item>
<rkts>620</rkts>
<ref>W50.73</ref>
<loc>Pander Pantheon 50 (1111). / Wanli Kanjur, rgyud, vol. YA, fol.188a5-188a6</loc>
<tib>'brum bu'i nad zhi bar byed pa'i gzungs</tib>
<skttrans></skttrans>
<coloph>'brum bu'i nad zhi bar byed pa'i gzungs rdzogs s.ho</coloph>
<note></note>
</item>

<item>
<rkts>615</rkts>
<ref>W50.74</ref>
<loc>Pander Pantheon 50 (1111). / Wanli Kanjur, rgyud, vol. YA, fol.188a6-189a7</loc>
<tib>'phags pa gzhang 'brum rab tu zhi bar byed pa'i mdo</tib>
<skttrans></skttrans>
<coloph>'phags pa gzhang 'brurn rab tu zhi byed pa'i mdo rdzogs s.ho // // rgya gar gyi mkhan po 'dzi na mi tra dang / da na shI la dang / zhu chen gyi lo tstsha ba ban dhe ye shes sdes bsgyur cing zhus te gtan la phab pa</coloph>
<note></note>
</item>

<item>
<rkts>778</rkts>
<ref>W50.75</ref>
<loc>Pander Pantheon 50 (1111). / Wanli Kanjur, rgyud, vol. YA, fol.189a7-189b1</loc>
<tib>ma zhu ba'i nad 'byang ba'i gzungs</tib>
<skttrans></skttrans>
<coloph>ma zhu ba'i nad 'byang ba'i gzungs rdzogs s.ho</coloph>
<note></note>
</item>

<item>
<rkts>779</rkts>
<ref>W50.76</ref>
<loc>Pander Pantheon 50 (1111). / Wanli Kanjur, rgyud, vol. YA, fol.189b1-189b3</loc>
<tib>'phags pa sdang ba thams cad rab tu zhi bar byed pa zhes bya ba'i gzungs</tib>
<skttrans></skttrans>
<coloph>'phags pa sdang ba thams cad rab tu zhi bar byed pa zhes bya ba'i gzungs rdzogs s.ho</coloph>
<note></note>
</item>

<item>
<rkts>780</rkts>
<ref>W50.77</ref>
<loc>Pander Pantheon 50 (1111). / Wanli Kanjur, rgyud, vol. YA, fol.189b3-189b5</loc>
<tib>sdig pa thams cad rab zhi bar byed pa zhes bya ba'i gzungs</tib>
<skttrans></skttrans>
<coloph>sdig pa thams cad rab zhi bar byed pa zhes bya ba'i gzungs rdzogs s.ho</coloph>
<note></note>
</item>

<item>
<rkts>1024</rkts>
<ref>W50.78</ref>
<loc>Pander Pantheon 50 (1111). / Wanli Kanjur, rgyud, vol. YA, fol.189b5-190a6</loc>
<tib>sdug bsngal thams cad rab tu zhi bar byed pa zhes bya ba'i gzungs</tib>
<skttrans></skttrans>
<coloph>sdug bsngal thams cad rab tu zhi bar byed pa zhes bya ba'i gzungs / bcom ldan 'das shakya thub pa'i zhal nas gsungs ba rdzogs s.ho</coloph>
<note></note>
</item>

<item>
<rkts>781</rkts>
<ref>W50.79</ref>
<loc>Pander Pantheon 50 (1111). / Wanli Kanjur, rgyud, vol. YA, fol.190a6-190a7</loc>
<tib>khro ba zhi bar byed ba'i gzungs</tib>
<skttrans></skttrans>
<coloph>khro ba zhi bar byed ba'i gzungs rdzogs s.ho</coloph>
<note></note>
</item>

<item>
<rkts>782</rkts>
<ref>W50.80</ref>
<loc>Pander Pantheon 50 (1111). / Wanli Kanjur, rgyud, vol. YA, fol.190a4-190b1</loc>
<tib>'phags pa khros pa zhi bar byed pa'i gzungs</tib>
<skttrans></skttrans>
<coloph>'phags pa khros pa zhi bar byed pa'i gzungs rdzogs s.ho</coloph>
<note></note>
</item>

<item>
<rkts>783</rkts>
<ref>W50.81</ref>
<loc>Pander Pantheon 50 (1111). / Wanli Kanjur, rgyud, vol. YA, fol.190b1-190b4</loc>
<tib>tshig btsan pa'i gzungs</tib>
<skttrans></skttrans>
<coloph>tshig btsan pa'i gzungs rdzogs s.ho</coloph>
<note></note>
</item>

<item>
<rkts>784</rkts>
<ref>W50.82</ref>
<loc>Pander Pantheon 50 (1111). / Wanli Kanjur, rgyud, vol. YA, fol.190b4-190b5</loc>
<tib>bdag srung ba'i gzungs</tib>
<skttrans></skttrans>
<coloph>bdag srung ba'i gzungs rdzogs s.ho</coloph>
<note></note>
</item>

<item>
<rkts>788</rkts>
<ref>W50.83</ref>
<loc>Pander Pantheon 50 (1111). / Wanli Kanjur, rgyud, vol. YA, fol.190b5-191a4</loc>
<tib>las grub pa'i gzungs</tib>
<skttrans></skttrans>
<coloph>las grub pa'i gzungs rdzogs s.ho</coloph>
<note></note>
</item>

<item>
<rkts>774</rkts>
<ref>W50.84</ref>
<loc>Pander Pantheon 50 (1111). / Wanli Kanjur, rgyud, vol. YA, fol.191a4-191a6</loc>
<tib>gos brgya thob pa'i gzungs</tib>
<skttrans></skttrans>
<coloph>gos brgya thob pa'i gzungs rdzogs s.ho</coloph>
<note></note>
</item>

<item>
<rkts>775</rkts>
<ref>W50.85</ref>
<loc>Pander Pantheon 50 (1111). / Wanli Kanjur, rgyud, vol. YA, fol.191a6-191a7</loc>
<tib>mi dga' bar byed ba'i gzungs</tib>
<skttrans></skttrans>
<coloph>mi dga' bar byed ba'i gzungs rdzogs s.ho</coloph>
<note></note>
</item>

<item>
<rkts>785</rkts>
<ref>W50.86</ref>
<loc>Pander Pantheon 50 (1111). / Wanli Kanjur, rgyud, vol. YA, fol.191a7-191b1</loc>
<tib>'phags pa yid du 'ong ba zhes bya ba</tib>
<skttrans></skttrans>
<coloph></coloph>
<note></note>
</item>

<item>
<rkts></rkts>
<ref>W50.87</ref>
<loc>Pander Pantheon 50 (1111). / Wanli Kanjur, rgyud, vol. YA, fol.191b1-191b3</loc>
<tib></tib>
<skttrans></skttrans>
<coloph></coloph>
<note></note>
</item>

<item>
<rkts>790</rkts>
<ref>W50.88</ref>
<loc>Pander Pantheon 50 (1111). / Wanli Kanjur, rgyud, vol. YA, fol.191b3-191b5</loc>
<tib>bcings ba las grol ba'i gzungs</tib>
<skttrans></skttrans>
<coloph>bcings ba las grol ba'i gzungs rdzogs so</coloph>
<note></note>
</item>

<item>
<rkts>736</rkts>
<ref>W50.89</ref>
<loc>Pander Pantheon 50 (1111). / Wanli Kanjur, rgyud, vol. YA, fol.191b5-192a2</loc>
<tib>mchog thob pa'i rig sngags</tib>
<skttrans></skttrans>
<coloph>'phags pa mchog thob pa rdzogs s.ho</coloph>
<note></note>
</item>

<item>
<rkts>644</rkts>
<ref>W50.90</ref>
<loc>Pander Pantheon 50 (1111). / Wanli Kanjur, rgyud, vol. YA, fol.192a2-192b1</loc>
<tib>shes rab skyid pa zhes bya ba'i gzungs</tib>
<skttrans></skttrans>
<coloph>shes rab skyed pa zhes bya ba'i gzungs rdzogs s.ho // // rgya gar gyi mkhan po dznya na garbha dang lo tstsha ba ban dhe klu' i dbang los bsgyur rgya gar gyi mkhan po bi dya ka ra sing ha dang / zhu chen gyi lo tstsha ba ban dhe dc ba tsan tras zhus te gtan la phab pa</coloph>
<note></note>
</item>

<item>
<rkts></rkts>
<ref>W50.</ref>
<loc>Pander Pantheon 50 (1111). / Wanli Kanjur, rgyud, vol. YA, fol.</loc>
<tib></tib>
<skttrans></skttrans>
<coloph></coloph>
<note></note>
</item>

<item>
<rkts></rkts>
<ref>W50.</ref>
<loc>Pander Pantheon 50 (1111). / Wanli Kanjur, rgyud, vol. YA, fol.</loc>
<tib></tib>
<skttrans></skttrans>
<coloph></coloph>
<note></note>
</item>

<item>
<rkts></rkts>
<ref>W50.</ref>
<loc>Pander Pantheon 50 (1111). / Wanli Kanjur, rgyud, vol. YA, fol.</loc>
<tib></tib>
<skttrans></skttrans>
<coloph></coloph>
<note></note>
</item>

<item>
<rkts></rkts>
<ref>W50.</ref>
<loc>Pander Pantheon 50 (1111). / Wanli Kanjur, rgyud, vol. YA, fol.</loc>
<tib></tib>
<skttrans></skttrans>
<coloph></coloph>
<note></note>
</item>

<item>
<rkts></rkts>
<ref>W50.</ref>
<loc>Pander Pantheon 50 (1111). / Wanli Kanjur, rgyud, vol. YA, fol.</loc>
<tib></tib>
<skttrans></skttrans>
<coloph></coloph>
<note></note>
</item>

<item>
<rkts></rkts>
<ref>W50.</ref>
<loc>Pander Pantheon 50 (1111). / Wanli Kanjur, rgyud, vol. YA, fol.</loc>
<tib></tib>
<skttrans></skttrans>
<coloph></coloph>
<note></note>
</item>

<item>
<rkts></rkts>
<ref>W50.</ref>
<loc>Pander Pantheon 50 (1111). / Wanli Kanjur, rgyud, vol. YA, fol.</loc>
<tib></tib>
<skttrans></skttrans>
<coloph></coloph>
<note></note>
</item>

<item>
<rkts></rkts>
<ref>W50.</ref>
<loc>Pander Pantheon 50 (1111). / Wanli Kanjur, rgyud, vol. YA, fol.</loc>
<tib></tib>
<skttrans></skttrans>
<coloph></coloph>
<note></note>
</item>

<item>
<rkts></rkts>
<ref>W50.</ref>
<loc>Pander Pantheon 50 (1111). / Wanli Kanjur, rgyud, vol. YA, fol.</loc>
<tib></tib>
<skttrans></skttrans>
<coloph></coloph>
<note></note>
</item>

<item>
<rkts></rkts>
<ref>W50.</ref>
<loc>Pander Pantheon 50 (1111). / Wanli Kanjur, rgyud, vol. YA, fol.</loc>
<tib></tib>
<skttrans></skttrans>
<coloph></coloph>
<note></note>
</item>

<item>
<rkts></rkts>
<ref>W50.</ref>
<loc>Pander Pantheon 50 (1111). / Wanli Kanjur, rgyud, vol. YA, fol.</loc>
<tib></tib>
<skttrans></skttrans>
<coloph></coloph>
<note></note>
</item>



</outline>
